Workbook

Sheet solicitudes
A1: Id | B1: Proyecto | D1: Punto de conexión y Nivel de tensión (kV) | E1: Tipo (SAC/SUCTD) | F1: Estado | G1: Zona | H1: Clasificación (C1, C2, C3) | I1: Observación | J1: NUP | K1: Empresa Solicitante | L1: Tipo | M1: Estado Solicitud | N1: Fecha Recepción | O1: Capacidad [MW] | P1: Tipo Proyecto | Q1: Fecha Estimada Conexión | R1: Punto de Conexión | S1: Nivel de tension | T1: Barra | U1: Paño | V1: Región | W1: Comuna | X1: Segmento de Transmisión | Y1: Fecha emisión informe definitivo | Z1: Plazo obtención declaración en const | AA1: Prórroga plazo obtención declaración en const.
A2: 2662 | B2: BESS Monte Águila | K2: Grenergy Renovables Pacific Limitada | L2: SUCTD | M2: Solicitud ingresada | N2: 22 de julio de 2025 11:23:32 | O2: 240 | P2: Híbrido | Q2: 22 de enero de 2027 00:00:00 | R2: S/E Elevadora Monte Águila 33/220 kV | S2: 33 | T2: Barra media tensión | U2: por definir | V2: Biobío | W2: Cabrero | X2: Dedicada
A3: 2646 | B3: Retiros de Red CRCA Víctor Jara | K3: Grenergy Renovables Pacific Limitada | L3: FEHACIENTES | M3: Desistida | N3: 10 de julio de 2025 10:51:20 | O3: 200 | P3: Híbrido | Q3: 30 de septiembre de 2025 00:00:00 | R3: S/E Elevadora PFV Victor Jara | S3: 33 | T3: BP | U3: TBD | V3: Tarapacá | W3: Pozo Almonte | X3: Dedicada
A4: 2424 | B4: PFV Pinina | J4: 5534 | K4: Grenergy Renovables Pacific Limitada | L4: SAC | M4: Detenida a la espera de definición de ingeniería de la obra | N4: 6 de febrero de 2025 18:01:12 | O4: 90 | P4: Híbrido | Q4: 30 de julio de 2030 00:00:00 | R4: NUEVA S/E VALENTÍN LETELIER 154 | S4: 154 | T4: Barra principal | U4: por definir | V4: Maule | W4: Linares | X4: Nacional
A5: 2421 | B5: PFV SAMARA | J5: 5546 | K5: Grenergy Renovables Pacific Limitada | L5: SAC | M5: Rechazada | N5: 6 de febrero de 2025 17:58:03 | O5: 200 | P5: Híbrido | Q5: 30 de julio de 2030 00:00:00 | R5: NUEVA S/E MANUEL RODRIGUEZ | S5: 220 | T5: Barra Principal | U5: por definir | V5: Metropolitana de Santiago | W5: Tiltil | X5: Nacional
A6: 2418 | B6: PFV TAEL | J6: 5544 | K6: Grenergy Renovables Pacific Limitada | L6: SAC | M6: Rechazada | N6: 6 de febrero de 2025 17:56:45 | O6: 200 | P6: Híbrido | Q6: 31 de julio de 2030 00:00:00 | R6: MANUEL RODRIGUEZ 220 [kV] | S6: 220 | T6: Barra Principal | U6: por definir | V6: Metropolitana de Santiago | W6: Tiltil | X6: Nacional
A7: 2416 | B7: PFV JAOS | J7: 5536 | K7: Grenergy Renovables Pacific Limitada | L7: SAC | M7: Detenida a la espera de definición de ingeniería de la obra | N7: 6 de febrero de 2025 17:54:47 | O7: 90 | P7: Híbrido | Q7: 30 de julio de 2030 00:00:00 | R7: NUEVA S/E LLOLLEO 110 | S7: 110 | T7: Barra Principal | U7: Por definir | V7: Valparaiso | W7: San Antonio | X7: Nacional
A8: 2415 | B8: PFV DENEB | J8: 5545 | K8: Grenergy Renovables Pacific Limitada | L8: SAC | M8: Detenida a la espera de definición de ingeniería de la obra | N8: 6 de febrero de 2025 17:51:34 | O8: 90 | P8: Híbrido | Q8: 30 de julio de 2030 00:00:00 | R8: NUEVA S/E RELONCAVÍ 110 | S8: 110 | T8: Barra Principal | U8: Por definir | V8: Los Lagos | W8: Puerto Montt | X8: Nacional
A9: 2414 | B9: PFV Encina | J9: 5547 | K9: Grenergy Renovables Pacific Limitada | L9: SAC | M9: Detenida a la espera de definición de ingeniería de la obra | N9: 6 de febrero de 2025 17:48:30 | O9: 90 | P9: Híbrido | Q9: 30 de julio de 2030 00:00:00 | R9: NUEVA S/E VALENTÍN LETELIER 66 kV | S9: 66 | T9: Barra Principal | U9: por definir | V9: Maule | W9: Linares | X9: Nacional
A10: 2405 | B10: PFV AMAYA | J10: 5550 | K10: Grenergy Renovables Pacific Limitada | L10: SAC | M10: Detenida a la espera de definición de ingeniería de la obra | N10: 6 de febrero de 2025 17:44:29 | O10: 90 | P10: Híbrido | Q10: 31 de julio de 2030 00:00:00 | R10: S/E NOS 110 [kV] | S10: 110 | T10: Barra principal | U10: Por definir | V10: Metropolitana de Santiago | W10: San Bernardo | X10: Nacional
A11: 2242 | B11: PFV El Vencedor II | J11: 5360 | K11: Grenergy Renovables Pacific Limitada | L11: SAC | M11: Rechazada | N11: 22 de noviembre de 2024 16:14:23 | O11: 800 | P11: Híbrido | Q11: 30 de julio de 2030 00:00:00 | R11: PFV Vencedor II | S11: 220 | T11: Nueva Diagonal | U11: Por Definir | V11: Antofagasta | W11: Taltal | X11: Nacional
A12: 2240 | B12: PFV El Vencedor 1 | J12: 5362 | K12: Grenergy Renovables Pacific Limitada | L12: SAC | M12: Rechazada | N12: 22 de noviembre de 2024 16:14:21 | O12: 400 | P12: Híbrido | Q12: 30 de julio de 2030 00:00:00 | R12: S/E Parinas 220 kV | S12: 220 | T12: Nueva Media Diagonal | U12: Por Definir | V12: Antofagasta | W12: Taltal | X12: Nacional
A13: 2237 | B13: PFV Vanz | J13: 5369 | K13: Grenergy Renovables Pacific Limitada | L13: SAC | M13: Detenida a la espera de definición de ingeniería de la obra | N13: 22 de noviembre de 2024 16:14:18 | O13: 200 | P13: Híbrido | Q13: 30 de julio de 2030 00:00:00 | R13: S/E Monte Mina 220 kV | S13: 220 | T13: Por definir | U13: Por Definir | V13: Antofagasta | W13: Antofagasta | X13: Nacional
A14: 2238 | B14: PFV TITÁN | J14: 5358 | K14: Grenergy Renovables Pacific Limitada | L14: SAC | M14: Detenida a la espera de definición de ingeniería de la obra | N14: 22 de noviembre de 2024 16:14:18 | O14: 200 | P14: Híbrido | Q14: 31 de julio de 2030 00:00:00 | R14: S/E Entre Ríos 220 kV | S14: 220 | T14: TBD | U14: TBD | V14: Biobío | W14: Cabrero | X14: Nacional
A15: 2236 | B15: PFV ATOM | J15: 5370 | K15: Grenergy Renovables Pacific Limitada | L15: SAC | M15: Rechazada | N15: 22 de noviembre de 2024 16:14:17 | O15: 200 | P15: Híbrido | Q15: 30 de junio de 2030 00:00:00 | R15: S/E Entre Ríos 220 kV | S15: 220 | T15: TBD | U15: TBD | V15: Biobío | W15: Cabrero | X15: Nacional
A16: 2235 | B16: PFV TARVOS | J16: 5361 | K16: Grenergy Renovables Pacific Limitada | L16: SAC | M16: Rechazada | N16: 22 de noviembre de 2024 16:14:16 | O16: 200 | P16: Híbrido | Q16: 30 de junio de 2030 00:00:00 | R16: S/E Kimal 220 kV | S16: 220 | T16: TBD | U16: TBD | V16: Antofagasta | W16: Maria Elena | X16: Nacional
A17: 2234 | B17: PFV FOBOS | K17: Grenergy Renovables Pacific Limitada | L17: SAC | M17: Rechazada | N17: 22 de noviembre de 2024 16:14:15 | O17: 700 | P17: Híbrido | Q17: 30 de junio de 2030 00:00:00 | R17: S/E Kimal 220 kV | S17: 220 | T17: TBD | U17: TBD | V17: Antofagasta | W17: Maria Elena | X17: Nacional
A18: 2068 | B18: BESS Víctor Jara 200 MW 6.5 horas | J18: 5065 | K18: Grenergy Renovables Pacific Limitada | L18: FEHACIENTES | M18: Proyecto declarado en construccion | N18: 19 de julio de 2024 09:33:07 | O18: 200 | P18: Híbrido | Q18: 31 de enero de 2026 00:00:00 | R18: S/E Victor Jara 33 kV | S18: 33 | T18: BP | U18: TBD | V18: Tarapacá | W18: Pozo Almonte | X18: Dedicada | Z18: 02/2025
A19: 1919 | B19: BESS ORTOSIA | J19: 4814 | K19: Grenergy Renovables Pacific Limitada | L19: SAC | M19: Observaciones a Informe de Autorización de Conexión Preliminar | N19: 27 de marzo de 2024 13:06:12 | O19: 90 | P19: Híbrido | Q19: 31 de marzo de 2028 00:00:00 | R19: S/E Torquemada 110 KV | S19: 110 | T19: Barra Principal | U19: Por definir | V19: Valparaiso | W19: Concón | X19: Zonal
A20: 1912 | B20: PFV + BESS Triqueta | J20: 4806 | K20: Grenergy Renovables Pacific Limitada | L20: SUCTD | M20: Rechazada | N20: 19 de marzo de 2024 17:30:57 | O20: 130 | P20: Híbrido | Q20: 31 de agosto de 2026 00:00:00 | R20: S/E Triqueta entre las estructuras 112 y 113 de la línea Quillota - Piuquenes en 220 kV | S20: 220 | T20: Barra Principal | U20: JT1 | V20: Valparaiso | W20: Catemu | X20: Dedicada
A21: 1911 | B21: BESS Metis | J21: 4805 | K21: Grenergy Renovables Pacific Limitada | L21: SAC | M21: Proyecto autorizado para declararse en construcción | N21: 18 de marzo de 2024 11:55:07 | O21: 90 | P21: Híbrido | Q21: 31 de marzo de 2028 00:00:00 | R21: S/E Quillota 110 [kV] | S21: 110 | T21: Barra Principal | U21: Por definir | V21: Valparaiso | W21: Quillota | X21: Nacional | Y21: 26/12/2024 12:16:05 | Z21: 12/2026
A22: 1904 | B22: BESS Telesto II | J22: 4790 | K22: Grenergy Renovables Pacific Limitada | L22: SAC | M22: Proyecto autorizado para declararse en construcción | N22: 14 de marzo de 2024 14:49:31 | O22: 20 | P22: Híbrido | Q22: 31 de marzo de 2028 00:00:00 | R22: S/E Salamanca 23 [kV] | S22: 23 | T22: Barra Principal N°2 | U22: Nuevo Paño E8 | V22: Coquimbo | W22: Salamanca | X22: Zonal | Y22: 16/12/2024 08:40:55 | Z22: 12/2026
A23: 1865 | B23: Bess Kore | J23: 4734 | K23: Grenergy Renovables Pacific Limitada | L23: SAC | M23: Observaciones a Informe de Autorización de Conexión Preliminar | N23: 13 de febrero de 2024 11:20:35 | O23: 90 | P23: Híbrido | Q23: 31 de marzo de 2028 00:00:00 | R23: S/E Alto Jahuel 110 [kV] | S23: 110 | T23: Barra Principal | U23: Por definir | V23: Metropolitana de Santiago | W23: Buin | X23: Nacional
A24: 1864 | B24: Bess Carpo | J24: 4735 | K24: Grenergy Renovables Pacific Limitada | L24: SAC | M24: Proyecto autorizado para declararse en construcción | N24: 13 de febrero de 2024 11:12:44 | O24: 150 | P24: Híbrido | Q24: 31 de marzo de 2028 00:00:00 | R24: S/E Alto Jahuel 154 [kV] | S24: 154 | T24: Barra Principal | U24: Por Definir | V24: Metropolitana de Santiago | W24: Buin | X24: Nacional | Y24: 21/01/2025 18:32:23 | Z24: 01/2027
A25: 1863 | B25: BESS Tebe | J25: 4732 | K25: Grenergy Renovables Pacific Limitada | L25: SAC | M25: Observaciones a Informe de Autorización de Conexión Preliminar | N25: 13 de febrero de 2024 10:58:31 | O25: 200 | P25: Híbrido | Q25: 31 de marzo de 2028 00:00:00 | R25: S/E Alto Jahuel 220 kV | S25: 220 | T25: Barra Principal | U25: Por Definir | V25: Metropolitana de Santiago | W25: Buin | X25: Nacional
A26: 1856 | B26: BESS Elara | J26: 4723 | K26: Grenergy Renovables Pacific Limitada | L26: SAC | M26: Detenida a la espera de definición de ingeniería de la obra | N26: 9 de febrero de 2024 10:24:30 | O26: 90 | P26: Híbrido | Q26: 31 de marzo de 2028 00:00:00 | R26: S/E Totihue 66 kV | S26: 66 | T26: Barra Principal | U26: Por Definir | V26: Libertador General Bernardo OHiggins | W26: Rengo | X26: Zonal
A27: 1850 | B27: BESS Cálice | J27: 4718 | K27: Grenergy Renovables Pacific Limitada | L27: SAC | M27: Elaboración Informe de Autorización de Conexión Preliminar | N27: 2 de febrero de 2024 10:02:12 | O27: 90 | P27: Híbrido | Q27: 31 de marzo de 2028 00:00:00 | R27: S/E Caldera 110 kV | S27: 110 | T27: Barra Principal | U27: H4 | V27: Atacama | W27: Caldera | X27: Zonal
A28: 1827 | B28: BESS Calé | J28: 4684 | K28: Grenergy Renovables Pacific Limitada | L28: SAC | M28: Proyecto autorizado para declararse en construcción | N28: 12 de enero de 2024 01:04:04 | O28: 90 | P28: Híbrido | Q28: 31 de marzo de 2028 00:00:00 | R28: S/E Bajos de Mena 110 kV | S28: 110 | T28: Barra Principal | U28: Por definir | V28: Metropolitana de Santiago | W28: Puente Alto | X28: Zonal | Y28: 10/10/2024 11:18:10 | Z28: 10/2026
A29: 1826 | B29: BESS Hiperion | J29: 4683 | K29: Grenergy Renovables Pacific Limitada | L29: SAC | M29: Desarrollo de estudios y/o antecedentes | N29: 11 de enero de 2024 23:31:36 | O29: 90 | P29: Híbrido | Q29: 31 de marzo de 2028 00:00:00 | R29: S/E Las Canteras (Ex S/E Seccionadora Colina) 110 kV | S29: 110 | T29: Barra Principal | U29: por definir | V29: Metropolitana de Santiago | W29: Quilicura | X29: Zonal
A30: 1792 | B30: Ampliación PMG Yellowstone | J30: 4647 | K30: Grenergy Renovables Pacific Limitada | L30: FEHACIENTES | M30: Proyecto autorizado para declararse en construcción | N30: 18 de diciembre de 2023 12:56:49 | O30: 9 | P30: Híbrido | Q30: 30 de abril de 2025 00:00:00 | R30: S/E Yellowstone 13,2 kV | S30: 13 | T30: Barra Principal | U30: Por definir | V30: Libertador General Bernardo OHiggins | W30: Marchigüe | X30: Dedicada | Z30: 12/2024
A31: 1790 | B31: Ampliación BESS Gabriela 220 MW | J31: 4636 | K31: Grenergy Renovables Pacific Limitada | L31: FEHACIENTES | M31: Proyecto declarado en construccion | N31: 14 de diciembre de 2023 15:38:28 | O31: 220 | P31: Híbrido | Q31: 30 de junio de 2025 00:00:00 | R31: S/E Elevadora PFV Gabriela 33 kV | S31: 33 | T31: Barra Principal | U31: Por definir | V31: Antofagasta | W31: Sierra Gorda | X31: Dedicada | Z31: 07/2024
A32: 1789 | B32: BESS Víctor Jara 200 MW | J32: 4635 | K32: Grenergy Renovables Pacific Limitada | L32: FEHACIENTES | M32: Proyecto declarado en construccion | N32: 14 de diciembre de 2023 15:31:58 | O32: 200 | P32: Híbrido | Q32: 31 de enero de 2027 00:00:00 | R32: S/E Elevadora PFV Víctor Jara 33 kV | S32: 33 | T32: Barra Principal | U32: por definir | V32: Tarapacá | W32: Pozo Almonte | X32: Dedicada | Z32: 01/2026
A33: 1763 | B33: PFV Triqueta | J33: 4595 | K33: Grenergy Renovables Pacific Limitada | L33: SUCTD | M33: Rechazada | N33: 24 de noviembre de 2023 13:52:38 | O33: 130 | P33: Híbrido | Q33: 31 de agosto de 2026 00:00:00 | R33: Linea Quillota - Piuquenes | S33: 220 | T33: Barra Principal | U33: por definir | V33: Valparaiso | W33: Catemu | X33: Dedicada | Y33: 19/03/2024 17:36:18 | Z33: 03/2024
A34: 1735 | B34: BESS Sao | J34: 4566 | K34: Grenergy Renovables Pacific Limitada | L34: SAC | M34: Detenida a la espera de definición de ingeniería de la obra | N34: 3 de noviembre de 2023 20:22:04 | O34: 200 | P34: Híbrido | Q34: 30 de junio de 2027 00:00:00 | R34: S/E Tinguiririca 220 kV | S34: 220 | T34: Media diagonal | U34: por definir | V34: Libertador General Bernardo OHiggins | W34: Placilla | X34: Nacional
A35: 1734 | B35: BESS Nereida | J35: 4567 | K35: Grenergy Renovables Pacific Limitada | L35: SAC | M35: Detenida a la espera de definición de ingeniería de la obra | N35: 3 de noviembre de 2023 20:02:38 | O35: 90 | P35: Híbrido | Q35: 30 de junio de 2027 00:00:00 | R35: S/E Seccionadora El Guindal 110 kV | S35: 110 | T35: Barra Principal | U35: por definir | V35: Metropolitana de Santiago | W35: Buin | X35: Zonal
A36: 1732 | B36: Bess Proteo | K36: Grenergy Renovables Pacific Limitada | L36: SAC | M36: Desistida | N36: 3 de noviembre de 2023 20:00:57 | O36: 200 | P36: Híbrido | Q36: 30 de junio de 2027 00:00:00 | R36: Tinguiririca 220 kV | S36: 220 | T36: Media Diagonal | U36: por definir | V36: Libertador General Bernardo OHiggins | W36: Placilla | X36: Nacional
A37: 1730 | B37: BESS Proteo | J37: 4554 | K37: Grenergy Renovables Pacific Limitada | L37: SAC | M37: Detenida a la espera de definición de ingeniería de la obra | N37: 3 de noviembre de 2023 19:55:51 | O37: 50 | P37: Híbrido | Q37: 30 de junio de 2027 00:00:00 | R37: S/E Santa Cruz 66 kV | S37: 66 | T37: Barra principal | U37: por definir | V37: Libertador General Bernardo OHiggins | W37: Santa Cruz | X37: Zonal
A38: 1729 | B38: BESS Despina | J38: 4545 | K38: Grenergy Renovables Pacific Limitada | L38: SAC | M38: Detenida a la espera de definición de ingeniería de la obra | N38: 3 de noviembre de 2023 19:54:53 | O38: 90 | P38: Híbrido | Q38: 30 de junio de 2027 00:00:00 | R38: S/E Pachacama 110 kV | S38: 110 | T38: Barra Principal | U38: por definir | V38: Valparaiso | W38: La Calera | X38: Nacional
A39: 1727 | B39: 200 | K39: Grenergy Renovables Pacific Limitada | L39: SAC | M39: Desistida | N39: 3 de noviembre de 2023 19:51:22 | O39: 200 | P39: Híbrido | Q39: 30 de junio de 2027 00:00:00 | R39: Tinguiririca 220 kV | S39: 220 | T39: media diagonal | U39: por definir | V39: Libertador General Bernardo OHiggins | W39: Placilla | X39: Nacional
A40: 1726 | B40: BESS Talasa | J40: 4529 | K40: Grenergy Renovables Pacific Limitada | L40: SAC | M40: Detenida a la espera de definición de ingeniería de la obra | N40: 3 de noviembre de 2023 19:49:45 | O40: 90 | P40: Híbrido | Q40: 30 de junio de 2027 00:00:00 | R40: S/E El Pimiento 110kV | S40: 110 | T40: Barra Principal | U40: por definir | V40: Metropolitana de Santiago | W40: Melipilla | X40: Nacional
A41: 1723 | B41: BESS Neso | J41: 4562 | K41: Grenergy Renovables Pacific Limitada | L41: SAC | M41: Detenida a la espera de definición de ingeniería de la obra | N41: 3 de noviembre de 2023 19:36:38 | O41: 150 | P41: Híbrido | Q41: 30 de junio de 2027 00:00:00 | R41: S/E Linderos 154 kV | S41: 154 | T41: Linderos | U41: por definir | V41: Metropolitana de Santiago | W41: Buin | X41: Zonal
A42: 1721 | B42: PV+BESS Hipocampo | J42: 4540 | K42: Grenergy Renovables Pacific Limitada | L42: SAC | M42: Rechazada | N42: 3 de noviembre de 2023 19:30:14 | O42: 90 | P42: Híbrido | Q42: 30 de junio de 2027 00:00:00 | R42: S/E Nueva Litueche 110 kV | S42: 110 | T42: SE Litueche | U42: por definir | V42: Libertador General Bernardo OHiggins | W42: Litueche | X42: Zonal
A43: 1700 | B43: BESS Tritón | J43: 4550 | K43: Grenergy Renovables Pacific Limitada | L43: SAC | M43: Detenida a la espera de definición de ingeniería de la obra | N43: 3 de noviembre de 2023 19:05:25 | O43: 200 | P43: Híbrido | Q43: 30 de junio de 2027 00:00:00 | R43: S/E Seccionadora El Pimiento 220 kV | S43: 220 | T43: Media Diagonal | U43: por definir | V43: Metropolitana de Santiago | W43: Melipilla | X43: Nacional
A44: 1600 | B44: BESS Bio Bio | J44: 4384 | K44: Grenergy Renovables Pacific Limitada | L44: SAC | M44: Proyecto autorizado para declararse en construcción | N44: 4 de septiembre de 2023 17:10:48 | O44: 90 | P44: Híbrido | Q44: 31 de diciembre de 2027 00:00:00 | R44: S/E Lagunillas 220 kV | S44: 220 | T44: Media Diagonal J14-J15 | U44: J14-J15 | V44: Biobío | W44: Coronel | X44: Nacional | Y44: 15/07/2024 17:49:55 | Z44: 07/2026
A45: 1599 | B45: Bess Santa Rosa | J45: 4378 | K45: Grenergy Renovables Pacific Limitada | L45: SAC | M45: Rechazada | N45: 4 de septiembre de 2023 16:00:04 | O45: 90 | P45: Híbrido | Q45: 31 de diciembre de 2027 00:00:00 | R45: S/E Hualqui 220 kV | S45: 220 | T45: Paño J12 S/E Hualqui | U45: J12 | V45: Biobío | W45: Hualqui | X45: Zonal
A46: 1598 | B46: BESS Varón | J46: 4381 | K46: Grenergy Renovables Pacific Limitada | L46: SAC | M46: Detenida a la espera de definición de ingeniería de la obra | N46: 4 de septiembre de 2023 15:55:58 | O46: 90 | P46: Híbrido | Q46: 31 de diciembre de 2027 00:00:00 | R46: S/E La Pólvora 220 kV | S46: 220 | T46: Media diagonal J14-J15 | U46: J14-15 | V46: Valparaiso | W46: Valparaíso | X46: Nacional
A47: 1597 | B47: PFV + BESS Carrizalillo | J47: 4382 | K47: Grenergy Renovables Pacific Limitada | L47: SAC | M47: Detenida a la espera de definición de ingeniería de la obra | N47: 4 de septiembre de 2023 15:49:03 | O47: 150 | P47: Híbrido | Q47: 31 de diciembre de 2027 00:00:00 | R47: S/E Don Héctor 220 kV | S47: 220 | T47: Media Diagonal J20-J21 | U47: J20-J21 | V47: Atacama | W47: Vallenar | X47: Nacional
A48: 1470 | B48: PMG Taruca | J48: 4100 | K48: Grenergy Renovables Pacific Limitada | L48: SUCTD | M48: Audiencia y antecedentes adicionales | N48: 4 de mayo de 2023 10:41:20 | O48: 9 | P48: Híbrido | Q48: 30 de junio de 2026 00:00:00 | R48: S/E Tap Off La Cruz 23 kV | S48: 23 | T48: Barra 23 kV | U48: E2 | V48: Antofagasta | W48: Maria Elena | X48: Dedicada
A49: 1469 | B49: PMG Chungungo | J49: 4099 | K49: Grenergy Renovables Pacific Limitada | L49: SUCTD | M49: Evaluación Admisibilidad | N49: 3 de mayo de 2023 17:52:44 | O49: 9 | P49: Solar | Q49: 31 de diciembre de 2026 00:00:00 | R49: S/E Minera Franke 23 kV | S49: 23 | T49: n/i | U49: E6 | V49: Antofagasta | W49: Taltal | X49: Dedicada
A50: 1364 | B50: PFV Monte Águila | J50: 3904 | K50: Grenergy Renovables Pacific Limitada | L50: SUCTD | M50: Proyecto Autorizado para Declararse en Construcción | N50: 30 de diciembre de 2022 00:40:39 | O50: 240 | P50: Solar | Q50: 31 de agosto de 2026 00:00:00 | R50: Línea 2x220 kV Santa María - Charrúa | S50: 220 | T50: Barra Principal | U50: JT1 | V50: Biobío | W50: Cabrero | X50: Dedicada | Y50: 07/06/2023 15:53:32 | Z50: 04/2025 | AA50: 10/2026
A51: 1353 | B51: PFV Gabriela | J51: 3849 | K51: Grenergy Renovables Pacific Limitada | L51: SUCTD | M51: Proyecto declarado en construcción | N51: 9 de diciembre de 2022 13:40:15 | O51: 220 | P51: Solar | Q51: 31 de agosto de 2026 00:00:00 | R51: Línea El Cobre - Gaby 220 kV | S51: 220 | T51: Derivación a 9 km de Gaby | U51: N/A | V51: Antofagasta | W51: Sierra Gorda | X51: Dedicada | Y51: 16/08/2023 17:06:51 | Z51: 08/2025
A52: 1336 | B52: PFV Bonasort | J52: 3811 | K52: Grenergy Renovables Pacific Limitada | L52: SUCTD | M52: Rechazada | N52: 16 de noviembre de 2022 12:39:33 | O52: 6.8 | P52: Solar | Q52: 31 de octubre de 2024 00:00:00 | R52: S/E Aguas Blancas 13 kV | S52: 13 | T52: Celda | U52: Celda a definir | V52: Antofagasta | W52: Antofagasta | X52: Dedicada | Y52: 20/03/2023 15:07:36 | Z52: 03/2023
A53: 1275 | B53: PFV La Ruca | J53: 3680 | K53: Grenergy Renovables Pacific Limitada | L53: SAC | M53: Detenida a la espera de definición de ingeniería de la obra | N53: 14 de septiembre de 2022 17:58:03 | O53: 100 | P53: Solar | Q53: Fecha inválida | R53: S/E Seccionadora La Ruca 110 kV | S53: 110 | T53: Barra principal | U53: H8 | V53: Coquimbo | W53: Ovalle | X53: Zonal
A54: 1273 | B54: PFV Buli | J54: 3679 | K54: Grenergy Renovables Pacific Limitada | L54: SAC | M54: Rechazada | N54: 14 de septiembre de 2022 17:46:21 | O54: 150 | P54: Solar | Q54: Fecha inválida | R54: S/E Seccionadora Buli 154 kV | S54: 154 | T54: Barra principal | U54: H6 | V54: Ñuble | W54: San Carlos | X54: Zonal
A55: 1272 | B55: PFV Chanqueahue | J55: 3677 | K55: Grenergy Renovables Pacific Limitada | L55: SAC | M55: Detenida a la espera de definición de ingeniería de la obra | N55: 14 de septiembre de 2022 17:45:39 | O55: 250 | P55: Solar | Q55: Fecha inválida | R55: S/E Seccionadora Totihue 220 kV | S55: 220 | T55: Barra 2 | U55: H1 | V55: Libertador General Bernardo OHiggins | W55: Rengo | X55: Zonal
A56: 1271 | B56: PFV Rumay | J56: 3676 | K56: Grenergy Renovables Pacific Limitada | L56: SAC | M56: Rechazada | N56: 14 de septiembre de 2022 17:44:31 | O56: 250 | P56: Solar | Q56: Fecha inválida | R56: S/E Don Goyo 220 kV | S56: 220 | T56: Barra 2 | U56: J10 | V56: Coquimbo | W56: Ovalle | X56: Zonal
A57: 1186 | B57: PFV Jicuri | J57: 3500 | K57: Grenergy Renovables Pacific Limitada | L57: SUCTD | M57: Rechazada | N57: 15 de junio de 2022 19:21:20 | O57: 90 | P57: Solar | Q57: 31 de diciembre de 2024 00:00:00 | R57: Línea Central Los Cipreses - Itahue | S57: 154 | T57: Circuito C2 | U57: 1 paño por definir | V57: Maule | W57: Río Claro | X57: Dedicada | Y57: 21/03/2023 21:55:39 | Z57: 03/2023
A58: 1184 | B58: PV Triqueta | J58: 3495 | K58: Grenergy Renovables Pacific Limitada | L58: SUCTD | M58: Rechazada | N58: 10 de junio de 2022 19:39:00 | O58: 130 | P58: Solar | Q58: 31 de diciembre de 2024 00:00:00 | R58: Línea Quillota - Los Piuquenes | S58: 220 | T58: doble barra | U58: por definir | V58: Valparaiso | W58: Catemu | X58: Dedicada
A59: 1156 | B59: PFV Lamida | J59: 3426 | K59: Grenergy Renovables Pacific Limitada | L59: SUCTD | M59: Rechazada | N59: 29 de abril de 2022 11:17:00 | O59: 200 | P59: Solar | Q59: 31 de diciembre de 2024 00:00:00 | R59: Línea ralco - Charrúa 220 kV | S59: 220 | T59: Circuito C1 | U59: C1 | V59: Biobío | W59: Quilleco | X59: Dedicada
A60: 1039 | B60: PFV Manto Solar | J60: 2984 | K60: Grenergy Renovables Pacific Limitada | L60: SUCTD | M60: Rechazada | N60: 21 de septiembre de 2021 18:31:04 | O60: 58 | P60: Solar | Q60: 30 de diciembre de 2023 00:00:00 | R60: Linea tap Barriles - Mantos de la Luna | S60: 110 | T60: Derivacion | U60: Derivacion | V60: Antofagasta | W60: Tocopilla | X60: Dedicada
A61: 1032 | B61: PFV San Carlos | J61: 2964 | K61: Grenergy Renovables Pacific Limitada | L61: SAC | M61: Rechazada | N61: 8 de septiembre de 2021 09:50:53 | O61: 50 | P61: Solar | Q61: 31 de diciembre de 2023 00:00:00 | R61: S/E San Carlos 66 kV | S61: 66 | T61: Ampliación de barra definido en el Decreto 418/2017 | U61: Nuevo paño de conexión | V61: Ñuble | W61: San Carlos | X61: Zonal | Y61: 26/03/2024 00:00:00 | Z61: 03/2023
A62: 1019 | B62: PE Lawal 100 MW fase 2 | J62: 2813 | K62: Grenergy Renovables Pacific Limitada | L62: SAC | M62: Rechazada | N62: 12 de agosto de 2021 19:38:23 | O62: 100 | P62: Eólico | Q62: 31 de diciembre de 2026 00:00:00 | R62: SE Nueva Pichirropulli | S62: 220 | T62: Barra principal | U62: Por definir | V62: Los Ríos | W62: Paillaco | X62: Zonal
A63: 1016 | B63: PE Demeter 50 MW | K63: Grenergy Renovables Pacific Limitada | L63: SAC | M63: Rechazada | N63: 11 de agosto de 2021 12:17:10 | O63: 50 | P63: Eólico | Q63: 31 de diciembre de 2025 00:00:00 | R63: SE Coiquen | S63: 66 | T63: Barra principal | U63: B2 | V63: Ñuble | W63: Quirihue | X63: Zonal
A64: 1015 | B64: PE Eleusis 300 MW | K64: Grenergy Renovables Pacific Limitada | L64: SAC | M64: Rechazada | N64: 11 de agosto de 2021 12:00:31 | O64: 300 | P64: Eólico | Q64: 26 de febrero de 2027 00:00:00 | R64: SE Don Goyo | S64: 220 | T64: Barra 1 | U64: J9 | V64: Coquimbo | W64: Ovalle | X64: Nacional
A65: 815 | B65: PFV Amanita dos | J65: 2514 | K65: Grenergy Renovables Pacific Limitada | L65: SAC | M65: Rechazada | N65: 12 de febrero de 2021 16:33:06 | O65: 30 | P65: Solar | Q65: 30 de diciembre de 2022 00:00:00 | R65: SE Lo Prado | S65: 44 | T65: Barra principal | U65: C4 | V65: Metropolitana de Santiago | W65: Pudahuel | X65: Zonal
A66: 661 | B66: PFV El Indio 80 MW | K66: Grenergy Renovables Pacific Limitada | L66: SAC | M66: Desistida | N66: 5 de octubre de 2020 13:57:33 | O66: 80 | P66: Solar | Q66: 30 de diciembre de 2021 00:00:00 | R66: SE La Ruca | S66: 110 | T66: Barra 1 | U66: H6 | V66: Coquimbo | W66: Ovalle | X66: Zonal
A67: 660 | B67: PFV Tamango 40 MW | J67: 2303 | K67: Grenergy Renovables Pacific Limitada | L67: SAC | M67: Proyecto declarado en construcción | N67: 5 de octubre de 2020 13:00:37 | O67: 40 | P67: Solar | Q67: 30 de diciembre de 2021 00:00:00 | R67: SE Paso Hondo | S67: 66 | T67: Barra 1 | U67: B2 | V67: Maule | W67: Retiro | X67: Zonal | Y67: 24/03/2023 15:38:56 | Z67: 09/2023
A68: 575 | B68: PFV Tamango 40 MW | K68: Grenergy Renovables Pacific Limitada | L68: SAC | M68: Rechazada | N68: 19 de agosto de 2020 00:40:40 | O68: 40 | P68: Solar | Q68: 29 de diciembre de 2021 00:00:00 | R68: SE Tap Off Tamango 66 kV | S68: 66 | T68: Barra principal | U68: Por definir | V68: Maule | W68: Cauquenes | X68: Zonal
A69: 574 | B69: PFV Caspana 40 MW | K69: Grenergy Renovables Pacific Limitada | L69: SAC | M69: Rechazada | N69: 19 de agosto de 2020 00:35:39 | O69: 40 | P69: Solar | Q69: 29 de diciembre de 2021 00:00:00 | R69: SE Tap Off Caspana 66 kV | S69: 66 | T69: Barra principal | U69: Por definir | V69: Ñuble | W69: Bulnes | X69: Zonal
A70: 573 | B70: PFV Socaire 35 MW | K70: Grenergy Renovables Pacific Limitada | L70: SAC | M70: Rechazada | N70: 19 de agosto de 2020 00:30:50 | O70: 35 | P70: Solar | Q70: 29 de diciembre de 2021 00:00:00 | R70: SE Tap Off Socaire 66 kV | S70: 66 | T70: Barra principal | U70: Por definir | V70: Maule | W70: Longaví | X70: Zonal
A71: 564 | B71: PFV Lascar 50 MW | K71: Grenergy Renovables Pacific Limitada | L71: SAC | M71: Rechazada | N71: 13 de agosto de 2020 18:06:00 | O71: 50 | P71: Solar | Q71: 29 de diciembre de 2021 00:00:00 | R71: SE Tap Off Lascar 66 kV | S71: 66 | T71: Barra principal | U71: Por definir | V71: Libertador General Bernardo OHiggins | W71: Peralillo | X71: Zonal
A72: 563 | B72: PFV Llaima 40 MW | K72: Grenergy Renovables Pacific Limitada | L72: SAC | M72: Desistida | N72: 13 de agosto de 2020 17:46:18 | O72: 40 | P72: Solar | Q72: 29 de diciembre de 2021 00:00:00 | R72: SE Tap Off Llaima 66 kV | S72: 66 | T72: Barra principal | U72: Por definir | V72: Maule | W72: San Javier | X72: Zonal
A73: 562 | B73: PFV Trapiche 150 MW | K73: Grenergy Renovables Pacific Limitada | L73: SUCTD | M73: Desistida | N73: 13 de agosto de 2020 16:44:16 | O73: 150 | P73: Solar | Q73: 29 de diciembre de 2021 00:00:00 | R73: SE Seccionadora Trapiche 220 kV | S73: 220 | T73: Barra principal | U73: Por definir | V73: Valparaiso | W73: Petorca | X73: Dedicada
A74: 561 | B74: PE Llancahue 40 MW | K74: Grenergy Renovables Pacific Limitada | L74: SAC | M74: Desistida | N74: 13 de agosto de 2020 16:29:26 | O74: 40 | P74: Eólico | Q74: 29 de diciembre de 2021 00:00:00 | R74: SE El Laurel (Nueva Valdivia) 66 kV | S74: 66 | T74: Barra N 1 | U74: B1 | V74: Los Ríos | W74: Valdivia | X74: Zonal
A75: 557 | B75: PFV Victor Jara 200 MW | J75: 2139 | K75: Grenergy Renovables Pacific Limitada | L75: SAC | M75: Proyecto declarado en construcción | N75: 12 de agosto de 2020 14:24:19 | O75: 200 | P75: Solar | Q75: 31 de enero de 2023 00:00:00 | R75: SE Pozo Almonte 220 kV | S75: 220 | T75: Barra sección N2 | U75: J4 | V75: Tarapacá | W75: Pozo Almonte | X75: Zonal | Y75: 29/12/2022 12:25:30 | Z75: 01/2024 | AA75: 01/2025
A76: 555 | B76: PE Anti 75 MW | J76: 2194 | K76: Grenergy Renovables Pacific Limitada | L76: SUCTD | M76: Rechazada | N76: 10 de agosto de 2020 14:39:42 | O76: 75 | P76: Eólico | Q76: 20 de marzo de 2025 00:00:00 | R76: SE Antillanca 110 kV | S76: 110 | T76: Barra principal | U76: por definir | V76: Los Lagos | W76: Puyehue | X76: Dedicada
A77: 549 | B77: PE Corcovado 60 MW | K77: Grenergy Renovables Pacific Limitada | L77: SAC | M77: Desistida | N77: 4 de agosto de 2020 19:19:09 | O77: 60 | P77: Eólico | Q77: 30 de diciembre de 2021 00:00:00 | R77: SE La mision 66 kV | S77: 66 | T77: Barra 2 | U77: B6 | V77: Los Lagos | W77: Osorno | X77: Zonal
A78: 530 | B78: PMG Clementine 9 MW | J78: 2083 | K78: Grenergy Renovables Pacific Limitada | L78: SAC | M78: Rechazada | N78: 9 de julio de 2020 15:35:32 | O78: 9 | P78: Solar | Q78: 1 de diciembre de 2021 00:00:00 | R78: SE San Clemente 13,8 kV | S78: 13 | T78: Barra principal | U78: por definir | V78: Maule | W78: San Clemente | X78: Zonal
A79: 529 | B79: PMG Yellowstone 7 MW | J79: 2086 | K79: Grenergy Renovables Pacific Limitada | L79: SAC | M79: Proyecto declarado en construcción | N79: 9 de julio de 2020 15:26:33 | O79: 7 | P79: Solar | Q79: 1 de diciembre de 2021 00:00:00 | R79: S/E Marchigue 13,2 kV | S79: 13 | T79: Barra Principal | U79: por definir | V79: Libertador General Bernardo OHiggins | W79: Marchigüe | X79: Zonal | Y79: 04/04/2022 09:52:36
A80: 583 | B80: PFV Queulat | J80: 1271 | K80: Grenergy Renovables Pacific Limitada | L80: SAC | M80: Rechazada | N80: 6 de julio de 2020 02:00:00 | O80: 80 | P80: Solar | Q80: 30 de marzo de 2025 00:00:00 | R80: S/E Nueva Casablanca | S80: 66 | T80: Barra 1 | U80: B3 | V80: Valparaiso | W80: Casablanca | X80: Zonal
A81: 230 | B81: PMG Parque Fotovoltaico Pampa Unión | J81: 1729 | K81: Grenergy Renovables Pacific Limitada | L81: SUCTD | M81: Desistida | N81: 1 de julio de 2020 00:00:00 | O81: 9 | P81: Solar | Q81: 11 de enero de 2021 00:00:00 | R81: S/E Sierra Gorda 33 kV | S81: 33 | T81: N/I | U81: N/I | V81: Antofagasta | W81: Sierra Gorda | X81: Dedicada
A82: 231 | B82: PMG Parque Fotovoltaico Pudu | J82: 1730 | K82: Grenergy Renovables Pacific Limitada | L82: SUCTD | M82: Rechazada | N82: 1 de julio de 2020 00:00:00 | O82: 9 | P82: Solar | Q82: 11 de enero de 2021 00:00:00 | R82: S/E Lince 23 kV | S82: 23 | T82: N/I | U82: N/I | V82: Antofagasta | W82: Mejillones | X82: Dedicada
A83: 441 | B83: PMG PFV Saya | J83: 1959 | K83: Grenergy Renovables Pacific Limitada | L83: SUCTD | M83: Rechazada | N83: 4 de mayo de 2020 00:00:00 | O83: 9 | P83: Solar | Q83: 30 de noviembre de 2021 00:00:00 | R83: S/E Tap Off Dolores 23 kV | S83: 23 | T83: Barra principal | U83: N/I | V83: Tarapacá | W83: Huara | X83: Zonal
A84: 442 | B84: PMG PFV Zapiga | J84: 1960 | K84: Grenergy Renovables Pacific Limitada | L84: SUCTD | M84: Rechazada | N84: 4 de mayo de 2020 00:00:00 | O84: 9 | P84: Solar | Q84: 30 de noviembre de 2021 00:00:00 | R84: S/E Tap Off Dolores 23 kV | S84: 23 | T84: Barra principal | U84: N/I | V84: Tarapacá | W84: Huara | X84: Zonal
A85: 453 | B85: PMG Saya | J85: 1959 | K85: Grenergy Renovables Pacific Limitada | L85: SAC | M85: Desistida | N85: 16 de abril de 2020 00:00:00 | O85: 9 | P85: Solar | Q85: 30 de noviembre de 2021 00:00:00 | R85: S/E Tap Off Dolores 23 kV | S85: 23 | T85: Barra principal | U85: N/I | V85: Tarapacá | W85: Huara | X85: Dedicada
A86: 454 | B86: PMG Zapiga | J86: 1960 | K86: Grenergy Renovables Pacific Limitada | L86: SAC | M86: Desistida | N86: 16 de abril de 2020 00:00:00 | O86: 9 | P86: Solar | Q86: 30 de noviembre de 2021 00:00:00 | R86: S/E Tap Off Dolores 23 kV | S86: 23 | T86: Barra principal | U86: N/I | V86: Tarapacá | W86: Huara | X86: Dedicada
A87: 391 | B87: PFV Lunar | J87: 1829 | K87: Grenergy Renovables Pacific Limitada | L87: SUCTD | M87: Rechazada | N87: 25 de febrero de 2020 00:00:00 | O87: 9 | P87: Solar | Q87: 20 de diciembre de 2022 00:00:00 | R87: S/E Mantos de la Luna 23 kV | S87: 23 | T87: Barra 1 | U87: N/I | V87: Antofagasta | W87: Tocopilla | X87: Dedicada | Y87: 29/09/2022 16:09:01 | Z87: 09/2022
A88: 392 | B88: PMG Taruca | J88: 1830 | K88: Grenergy Renovables Pacific Limitada | L88: SUCTD | M88: Rechazada | N88: 21 de febrero de 2020 00:00:00 | O88: 9 | P88: Solar | Q88: 30 de noviembre de 2021 00:00:00 | R88: S/E Tap Off La Cruz 23 kV | S88: 23 | T88: Barra 1 | U88: N/I | V88: Antofagasta | W88: Maria Elena | X88: Dedicada | Z88: 10/2022 | AA88: 04/2023
A89: 372 | B89: PE Lawal | J89: 1796 | K89: Grenergy Renovables Pacific Limitada | L89: SAC | M89: Rechazada | N89: 7 de febrero de 2020 00:00:00 | O89: 100 | P89: Solar | Q89: 28 de febrero de 2022 00:00:00 | R89: S/E Nueva Pichirropulli 220 kV | S89: 220 | T89: N/I | U89: J9 | V89: Los Ríos | W89: Paillaco | X89: Nacional
A90: 328 | B90: Parque Fotovoltaico Adelma | J90: 1773 | K90: Grenergy Renovables Pacific Limitada | L90: SAC | M90: Rechazada | N90: 16 de enero de 2020 00:00:00 | O90: 9 | P90: Solar | Q90: 11 de enero de 2020 00:00:00 | R90: S/E Linares Norte 13,2 kV | S90: 132 | T90: Barra 1 | U90: N/I | V90: Maule | W90: Linares | X90: Zonal
A91: 321 | B91: Parque Fotovoltaico Linar | J91: 1740 | K91: Grenergy Renovables Pacific Limitada | L91: SAC | M91: Rechazada | N91: 14 de enero de 2020 00:00:00 | O91: 9 | P91: Solar | Q91: 11 de enero de 2020 00:00:00 | R91: S/E Linares Norte 13,2 kV | S91: 132 | T91: Barra 1 | U91: N/I | V91: Maule | W91: Linares | X91: Zonal
A92: 233 | B92: Parque Fotovoltaico Mirador | J92: 1741 | K92: Grenergy Renovables Pacific Limitada | L92: SUCTD | M92: Proyecto declarado en construcción | N92: 14 de enero de 2020 00:00:00 | O92: 6 | P92: Solar | Q92: 20 de diciembre de 2023 00:00:00 | R92: S/E Mirador 23 kV - S/E Travesía | S92: 23 | T92: Barra 1 | U92: N/I | V92: Atacama | W92: Copiapó | X92: Dedicada | Y92: 13/05/2022 13:08:10 | Z92: 10/2022
A93: 234 | B93: PMG Parque Fotovoltaico Bonasort | J93: 1742 | K93: Grenergy Renovables Pacific Limitada | L93: SUCTD | M93: Rechazada | N93: 14 de enero de 2020 00:00:00 | O93: 9 | P93: Solar | Q93: 31 de diciembre de 2023 00:00:00 | R93: S/E Aguas Blancas 13,2 kV | S93: 13 | T93: Barra 1 | U93: Celda C8 proyectada | V93: Antofagasta | W93: Antofagasta | X93: Dedicada | Y93: 29/09/2022 15:59:29 | Z93: 09/2022
A94: 235 | B94: PMG Parque Fotovoltaico Flamenco | J94: 1743 | K94: Grenergy Renovables Pacific Limitada | L94: SUCTD | M94: Desistida | N94: 14 de enero de 2020 00:00:00 | O94: 9 | P94: Solar | Q94: 11 de enero de 2021 00:00:00 | R94: S/E Manto Verde | S94: 138 | T94: Barra 1 | U94: N/I | V94: Atacama | W94: Chañaral | X94: Dedicada
A95: 236 | B95: PMG Parque Fotovoltaico Puelma | J95: 1744 | K95: Grenergy Renovables Pacific Limitada | L95: SUCTD | M95: Desistida | N95: 14 de enero de 2020 00:00:00 | O95: 9 | P95: Solar | Q95: 11 de enero de 2021 00:00:00 | R95: S/E Spence 23 kV | S95: 23 | T95: Barra 1 23 kV | U95: N/I | V95: Antofagasta | W95: Sierra Gorda | X95: Dedicada
A96: 237 | B96: PMG Parque Fotovoltaico Tambillo | J96: 1745 | K96: Grenergy Renovables Pacific Limitada | L96: SUCTD | M96: Rechazada | N96: 14 de enero de 2020 00:00:00 | O96: 9 | P96: Solar | Q96: 11 de enero de 2021 00:00:00 | R96: S/E Jorquera 23 kV | S96: 23 | T96: Barra 23 kV | U96: N/I | V96: Atacama | W96: Tierra Amarilla | X96: Dedicada
A97: 229 | B97: PMG Travesía | J97: 1721 | K97: Grenergy Renovables Pacific Limitada | L97: SUCTD | M97: Proyecto declarado en construcción | N97: 27 de diciembre de 2019 00:00:00 | O97: 9 | P97: Solar | Q97: 11 de enero de 2021 00:00:00 | R97: S/E Travesía 23 kV | S97: 23 | T97: N/I | U97: N/I | V97: Atacama | W97: Copiapó | X97: Dedicada | Y97: 12/05/2022 19:41:09 | Z97: 10/2022
A98: 317 | B98: Parque Fotovoltaico Violeta | J98: 1710 | K98: Grenergy Renovables Pacific Limitada | L98: SAC | M98: Desistida | N98: 26 de diciembre de 2019 00:00:00 | O98: 250 | P98: Solar | Q98: 11 de enero de 2021 00:00:00 | R98: S/E Roncacho 220 kV | S98: 220 | T98: N/I | U98: Por definir | V98: Arica y Parinacota | W98: Camarones | X98: Nacional
A99: 293 | B99: PMG Parque Fotovoltaico Tamarugal | J99: 1664 | K99: Grenergy Renovables Pacific Limitada | L99: SAC | M99: Rechazada | N99: 19 de noviembre de 2019 00:00:00 | O99: 9 | P99: Solar | Q99: 8 de enero de 2021 00:00:00 | R99: S/E Tamarugal 23 kV | S99: 23 | T99: Barra 1 | U99: E6 | V99: Tarapacá | W99: Pozo Almonte | X99: Zonal
A100: 294 | B100: PMG Parque Fotovoltaico Tamarugal II | J100: 1665 | K100: Grenergy Renovables Pacific Limitada | L100: SAC | M100: Rechazada | N100: 19 de noviembre de 2019 00:00:00 | O100: 9 | P100: Solar | Q100: 11 de enero de 2021 00:00:00 | R100: S/E Tamarugal 23 kV | S100: 23 | T100: Barra 1 | U100: E7 | V100: Tarapacá | W100: Pozo Almonte | X100: Zonal
...

Sheet lista
B3: Region | C3: Macrozona
B4: 2. Tarapacá | C4: Norte
B5: 3. Antofagasta | C5: Norte
B6: 4. Atacama | C6: Norte
B7: 5. Coquimbo | C7: Norte
B8: 6. Valparaiso | C8: Centro
B9: 7. Metropolitana | C9: Centro
B10: 8. O´Higgins | C10: Centro
B11: 9. Maule | C11: Centro
B12: 11. BioBio | C12: Sur
B13: 12. La Araucania | C13: Sur
B14: 13. Los Rios | C14: Sur
B15: 14. Los Lagos | C15: Sur

Sheet Analisis SE 2025
B2: Id | C2: Proyecto | D2: Punto de conexión y Nivel de tensión (kV) | E2: Capacidad [MW] Solicitada | F2: Región | G2: Tecnología | H2: Tipo (SAC/SUCTD) | I2: Estado Tramitación | J2: Macro Zona | K2: Clasificación (C1, C2, C3) | L2: Observacion | M2: ¿Permite reconversión? | N2: Comentario adicional
B3: 1919 | C3: BESS Ortosia | D3: S/E Torquemada 110 KV | E3: 90 | F3: 6. Valparaiso | G3: BESS | H3: SAC | I3: Observaciones a Informe de Autorización de Conexión Preliminar. | J3: =VLOOKUP(F3,lista!$B$4:$C$15,2,FALSE) -> Centro | K3: C2 | L3: Proyecto en tramitación ante el CEN. A la espera de emisión de informes. | M3: No | N3: Terreno prospectado
B4: 1598 | C4: BESS Varón | D4: S/E La Pólvora 220 kV | E4: 90 | F4: 6. Valparaiso | G4: BESS | H4: SAC | I4: En espera de definición de ingeniería CEN | J4: =VLOOKUP(F4,lista!$B$4:$C$15,2,FALSE) -> Centro | K4: C2 | L4: Proyecto en etapa temprana. En espera que adjudicatario de las obras de ampliación avance con ingeniería. | M4: Si
B5: 1865 | C5: Bess Kore | D5: S/E Alto Jahuel 110 [kV] | E5: 90 | F5: 7. Metropolitana | G5: BESS | H5: SAC | I5: Observaciones a Informe de Autorización de Conexión Preliminar | J5: =VLOOKUP(F5,lista!$B$4:$C$15,2,FALSE) -> Centro | K5: C2 | L5: Proyecto BESS SA en estado avanzado, se insiste al CEN para emisión del Informe Definitivo. | M5: No
B6: 1864 | C6: Bess Carpo | D6: S/E Alto Jahuel 154 [kV] | E6: 150 | F6: 7. Metropolitana | G6: BESS | H6: SAC | I6: Proyecto autorizado para declararse en construcción | J6: =VLOOKUP(F6,lista!$B$4:$C$15,2,FALSE) -> Centro | K6: C2 | L6: Proyecto BESS SA en estado avanzado, en espera para Declararse en Construcción. | M6: No
B7: 1827 | C7: BESS Calé | D7: S/E Bajos de Mena 110 kV | E7: 90 | F7: 7. Metropolitana | G7: BESS | H7: SAC | I7: Proyecto autorizado para declararse en construcción | J7: =VLOOKUP(F7,lista!$B$4:$C$15,2,FALSE) -> Centro | K7: C2 | L7: Proyecto BESS SA en estado avanzado, en espera para Declararse en Construcción. | M7: No | N7: Terreno proespectado, limitacion de plazo de conexión (propietario)
B8: 1826 | C8: BESS Hiperion | D8: S/E Las Canteras (Ex S/E Seccionadora Colina) 110 kV | E8: 90 | F8: 7. Metropolitana | G8: BESS | H8: SAC | I8: Desarrollo de estudios y/o antecedentes | J8: =VLOOKUP(F8,lista!$B$4:$C$15,2,FALSE) -> Centro | K8: C2 | L8: Proyecto en tramitación ante el CEN. | M8: Si | N8: Terreno costoso y datacenters en al zona
B9: 1275 | C9: PFV La Ruca | D9: S/E Seccionadora La Ruca 110 kV | E9: 100 | F9: 5. Coquimbo | G9: PFV + BESS | H9: SAC | I9: En espera de definición de ingeniería CEN | J9: =VLOOKUP(F9,lista!$B$4:$C$15,2,FALSE) -> Norte | K9: C3 | L9: Proyecto en etapa temprana. En espera que adjudicatario de las obras de ampliación avance con ingeniería. | M9: Si
B10: 2416 | C10: PFV JAOS | D10: NUEVA S/E LLOLLEO 110 | E10: 90 | F10: 6. Valparaiso | G10: PFV + BESS | H10: SAC | I10: En espera de definición de ingeniería CEN | J10: =VLOOKUP(F10,lista!$B$4:$C$15,2,FALSE) -> Centro | K10: C3 | L10: Proyecto en etapa temprana. En espera que adjudicatario de las obras de ampliación avance con ingeniería. | M10: Si
B11: 1729 | C11: BESS Despina | D11: S/E Pachacama 110 kV | E11: 90 | F11: 6. Valparaiso | G11: BESS | H11: SAC | I11: En espera de definición de ingeniería CEN | J11: =VLOOKUP(F11,lista!$B$4:$C$15,2,FALSE) -> Centro | K11: C3 | L11: Proyecto en etapa temprana. En espera que adjudicatario de las obras de ampliación avance con ingeniería. | M11: Si
B12: 1726 | C12: BESS Talasa | D12: S/E El Pimiento 110kV | E12: 90 | F12: 7. Metropolitana | G12: BESS | H12: SAC | I12: En espera de definición de ingeniería CEN | J12: =VLOOKUP(F12,lista!$B$4:$C$15,2,FALSE) -> Centro | K12: C3 | L12: Proyecto en etapa temprana. En espera que adjudicatario de las obras de ampliación avance con ingeniería. | M12: Si
B13: 1723 | C13: BESS Neso | D13: S/E Linderos 154 kV | E13: 150 | F13: 7. Metropolitana | G13: BESS | H13: SAC | I13: En espera de definición de ingeniería CEN | J13: =VLOOKUP(F13,lista!$B$4:$C$15,2,FALSE) -> Centro | K13: C3 | L13: Proyecto en etapa temprana. En espera que adjudicatario de las obras de ampliación avance con ingeniería. | M13: Si
B14: 1700 | C14: BESS Tritón | D14: S/E Seccionadora El Pimiento 220 kV | E14: 200 | F14: 7. Metropolitana | G14: BESS | H14: SAC | I14: En espera de definición de ingeniería CEN | J14: =VLOOKUP(F14,lista!$B$4:$C$15,2,FALSE) -> Centro | K14: C3 | L14: Proyecto en etapa temprana. En espera que adjudicatario de las obras de ampliación avance con ingeniería. | M14: Si
B15: 1730 | C15: BESS Proteo | D15: S/E Santa Cruz 66 kV | E15: 50 | F15: 8. O´Higgins | G15: BESS | H15: SAC | I15: En espera de definición de ingeniería CEN | J15: =VLOOKUP(F15,lista!$B$4:$C$15,2,FALSE) -> Centro | K15: C3 | L15: Proyecto en etapa temprana. En espera que adjudicatario de las obras de ampliación avance con ingeniería. | M15: Si
B16: 2414 | C16: PFV Encina | D16: NUEVA S/E VALENTÍN LETELIER 66 kV | E16: 90 | F16: 9. Maule | G16: PFV + BESS | H16: SAC | I16: En espera de definición de ingeniería CEN | J16: =VLOOKUP(F16,lista!$B$4:$C$15,2,FALSE) -> Centro | K16: C3 | L16: Proyecto en etapa temprana. En espera que adjudicatario de las obras de ampliación avance con ingeniería. | M16: Si
C18: Notas:
C19: - Los proyectos Clasificación "C2" podrían realizar una hibridación con Data Center una vez se Declaración en Construcción, resultando finalmente un proyecto del tipo Data Center + BESS.
C20: - Los proyectos clasificación "C3" podrían realizar una reconversión de teccnología sin necesidad de tener una Declaración en Construcción pudiendo resultar en un proyecto Data Center, Data Center + BESS u otro.
C22: Garantias: Para proyectos C2, la garantia esta comprometida a la conexión del proyecto. Proyectos en C3 es posible

Sheet DC Acceso abierto 2025
A2: ACCESO ABIERTO | B2: Proyecto | C2: NUP | D2: Empresa Solicitante | E2: Tipo | F2: Estado Solicitud | G2: Fecha Recepción | H2: Capacidad [MW] | I2: Tipo Proyecto | J2: Fecha Estimada Conexión | K2: Punto de Conexión | L2: Nivel de tension | M2: Barra | N2: Paño | O2: Región | P2: Comuna | Q2: Segmento de Transmisión | R2: Fecha emisión informe definitivo | S2: Plazo obtención declaración en const | T2: Prórroga plazo obtención declaración en const.
A3: 537 | B3: PROYECTO ODATA DATACENTER ST01 | C3: 2129 | D3: ODATA CHILE S.A. | E3: SAC | F3: Proyecto declarado en construcción | G3: 20 de julio de 2020 12:59:33 | H3: 30 | I3: Consumo | J3: 30 de junio de 2022 00:00:00 | K3: S/E Nueva Lampa 220 kV | L3: 220 | M3: Ambas Barras | N3: J7/J8 (Diagonal Nº3) | O3: Metropolitana de Santiago | P3: Lampa | Q3: Nacional | R3: 05/07/2023 15:44:07 | S3: 01/2024
A4: 854 | B4: ODATA DC ST02 | D4: ODATA CHILE S.A. | E4: SAC | F4: Rechazada | G4: 22 de marzo de 2021 21:05:24 | H4: 60 | I4: Consumo | J4: 30 de noviembre de 2023 00:00:00 | K4: S/E LO ESPEJO 110 kV | L4: 110 | M4: BARRAS 1 Y 2 | N4: 2 NUEVOS PAÑOS A CONSTRUIR | O4: Metropolitana de Santiago | P4: San Bernardo | Q4: Zonal
A5: 888 | B5: Datacenter Condor | C5: 2597 | D5: Microsoft Datacenter Chile SA | E5: SAC | F5: Desistida | G5: 13 de abril de 2021 14:34:17 | H5: 25 | I5: Consumo | J5: 1 de mayo de 2023 00:00:00 | K5: S/E Chacabuco 110kv | L5: 110 | M5: Doble Barra | N5: H3, H4 | O5: Metropolitana de Santiago | P5: Quilicura | Q5: Zonal | R5: 29/06/2022 10:32:23 | S5: 12/2022
A6: 1009 | B6: Datacenter Pisco | C6: 2801 | D6: Microsoft Datacenter Chile SA | E6: SAC | F6: Rechazada | G6: 27 de julio de 2021 15:10:55 | H6: 40 | I6: Consumo | J6: Fecha inválida | K6: S/E Chicureo 220 kV | L6: 220 | M6: Barra 1 y 2 | N6: J3, J4 | O6: Metropolitana de Santiago | P6: Colina | Q6: Zonal
A7: 1043 | B7: Datacenter Milagros | C7: 3000 | D7: Microsoft Datacenter Chile SA | E7: SUCTD | F7: Rechazada | G7: 8 de octubre de 2021 13:24:40 | H7: 40 | I7: Consumo | J7: 4 de julio de 2023 00:00:00 | K7: S/E Lampa | L7: 220 | M7: Barra Principal, seccion 1 y seccion 2 | N7: J3, J4 | O7: Metropolitana de Santiago | P7: Lampa | Q7: Dedicada | R7: 02/06/2023 12:20:44 | S7: 09/2024
A8: 1049 | B8: EDCSCL02_COLINA | D8: Edgeconnex Chile V SpA | E8: SAC | F8: Desistida | G8: 15 de octubre de 2021 16:08:01 | H8: 30 | I8: Consumo | J8: 15 de julio de 2023 00:00:00 | K8: S/E COLINA 110KV | L8: 110 | M8: DOBLE BARRA | N8: Por Definir | O8: Metropolitana de Santiago | P8: Colina | Q8: Zonal
A9: 1094 | B9: SCALA - Fase Inicial Sta Teresa DC | C9: 3156 | D9: Electrica Santa Teresa SpA | E9: SUCTD | F9: Rechazada | G9: 30 de diciembre de 2021 07:06:54 | H9: 20 | I9: Consumo | J9: 27 de septiembre de 2022 00:00:00 | K9: SE Lampa | L9: 23 | M9: Barra 1 y Barra 2 | N9: E1 y E2 | O9: Metropolitana de Santiago | P9: Lampa | Q9: Dedicada
A10: 1127 | B10: DC Huechuraba - Fase 1 | C10: 3384 | D10: Electrica Huechuraba SpA | E10: SAC | F10: Rechazada | G10: 1 de abril de 2022 15:19:18 | H10: 10 | I10: Consumo | J10: 6 de enero de 2023 00:00:00 | K10: S/E Recoleta 12 kV | L10: 12 | M10: Barra Principal N°3 y Barra Principal N°4 | N10: E21 (5-T3) y E30 (6-T4) | O10: Metropolitana de Santiago | P10: Huechuraba | Q10: Zonal
A11: 1130 | B11: DC Huechuraba - Fase 2 | C11: 3391 | D11: Electrica Huechuraba SpA | E11: SAC | F11: Rechazada | G11: 6 de abril de 2022 14:38:47 | H11: 60 | I11: Consumo | J11: 3 de noviembre de 2024 00:00:00 | K11: S/E El Salto 110 kV | L11: 110 | M11: Barras 1 y 2 Sección N°1 | N11: H3 y H4 | O11: Metropolitana de Santiago | P11: Huechuraba | Q11: Zonal | R11: 16/01/2023 17:52:20 | S11: 07/2024
A12: 1135 | B12: DC Padre Hurtado - Fase 2 | C12: 3409 | D12: Electrica Padre Hurtado SpA | E12: SAC | F12: Rechazada | G12: 21 de abril de 2022 11:37:33 | H12: 50 | I12: Consumo | J12: 30 de marzo de 2024 00:00:00 | K12: S/E Padre Hurtado 110 kV | L12: 110 | M12: Barra Principal | N12: H2 | O12: Metropolitana de Santiago | P12: Padre Hurtado | Q12: Zonal
A13: 1182 | B13: DC Padre Hurtado - Fase 3 | C13: 3491 | D13: Electrica Padre Hurtado SpA | E13: SAC | F13: Rechazada | G13: 9 de junio de 2022 17:51:57 | H13: 60 | I13: Consumo | J13: 30 de junio de 2024 00:00:00 | K13: S/E Santa Marta 110 kV | L13: 110 | M13: Barra Principal | N13: H3 | O13: Metropolitana de Santiago | P13: Padre Hurtado | Q13: Zonal
A14: 1286 | B14: DC Huechuraba - Fase 1 v01 | C14: 3685 | D14: Electrica Huechuraba SpA | E14: SAC | F14: Proyecto autorizado para declararse en construcción | G14: 22 de septiembre de 2022 16:32:34 | H14: 10 | I14: Consumo | J14: Fecha inválida | K14: S/E Recoleta 12 kV | L14: 12 | M14: Barra Principal N°3 12,5 kV | N14: E21 y E22 | O14: Metropolitana de Santiago | P14: Huechuraba | Q14: Zonal | R14: 22/06/2023 14:24:37 | S14: 09/2023 | T14: 09/2025
A15: 1516 | B15: Datacenter Pisco | C15: 4167 | D15: Microsoft Datacenter Chile SA | E15: SAC | F15: Elaboración Informe de Autorización de Conexión Preliminar | G15: 8 de junio de 2023 10:24:41 | H15: 50 | I15: Consumo | J15: 5 de julio de 2025 00:00:00 | K15: S/E Chicureo 220 kV | L15: 220 | M15: Barra principal 1 | N15: J3 | O15: Metropolitana de Santiago | P15: Colina | Q15: Zonal
A16: 2010 | B16: DC Curauma Fase 2 | C16: 4948 | D16: Scala Chile Data Centers SpA | E16: SAC | F16: Periodo de presentación de discrepancias | G16: 23 de mayo de 2024 15:20:42 | H16: 50 | I16: Consumo | J16: 15 de febrero de 2027 00:00:00 | K16: S/E Curauma 110 kV | L16: 110 | M16: Barra Principal, Paños H3 y H6 | N16: H3 y H6 | O16: Valparaiso | P16: Valparaíso | Q16: Zonal
A17: 2044 | B17: Datacenter Pisco 2 | C17: 5044 | D17: Microsoft Datacenter Chile SA | E17: SAC | F17: Proyecto autorizado para declararse en construcción | G17: 28 de junio de 2024 10:22:51 | H17: 50 | I17: Consumo | J17: 31 de julio de 2026 00:00:00 | K17: S/E Chicureo 220 kV | L17: 220 | M17: Barra 2 | N17: J4 | O17: Metropolitana de Santiago | P17: Colina | Q17: Zonal | R17: 14/04/2025 11:28:47 | S17: 10/2025
A18: 2179 | B18: Solution 2 | C18: 5260 | D18: ENSOLUTION SPA | E18: SAC | F18: Proyecto autorizado para declararse en construcción | G18: 15 de octubre de 2024 09:49:25 | H18: 450 | I18: Consumo | J18: 29 de diciembre de 2028 00:00:00 | K18: S/E Alto Jahuel 500 kV | L18: 500 | M18: Doble Barra + Barra Transferencia | N18: K7 | O18: Metropolitana de Santiago | P18: Buin | Q18: Nacional | R18: 04/07/2025 12:14:14 | S18: 06/2027
A19: 2325 | B19: Datacenter Condor 2 | C19: 5433 | D19: Microsoft Datacenter Chile SA | E19: SAC | F19: Observaciones a Informe de Autorización de Conexión Preliminar | G19: 19 de diciembre de 2024 17:00:01 | H19: 25 | I19: Consumo | J19: 17 de enero de 2027 00:00:00 | K19: SE Chacabuco 110kV | L19: 110 | M19: Doble barra | N19: H3, H4 | O19: Metropolitana de Santiago | P19: Quilicura | Q19: Zonal
A20: 2377 | B20: DC Valparaiso 1 | C20: 5497 | D20: FR DATA SpA | E20: SAC | F20: Detenida a la espera de definición de ingeniería de la obra | G20: 29 de enero de 2025 16:12:07 | H20: 200 | I20: Consumo | J20: 1 de abril de 2028 00:00:00 | K20: SE La Polvora | L20: 220 | M20: Barra principal N°2 | N20: J15 | O20: Valparaiso | P20: Valparaíso | Q20: Nacional
A21: 2378 | B21: DC Valparaiso 2 | C21: 5498 | D21: FR DATA SpA | E21: SAC | F21: Detenida a la espera de definición de ingeniería de la obra | G21: 29 de enero de 2025 16:19:36 | H21: 100 | I21: Consumo | J21: 1 de abril de 2028 00:00:00 | K21: SE La Polvora | L21: 220 | M21: Barra principal N°2 | N21: J18 | O21: Valparaiso | P21: Valparaíso | Q21: Nacional
A22: 2443 | B22: DC Alto Jahuel | C22: 5570 | D22: FR DATA SpA | E22: SAC | F22: Evaluación de antecedentes y/o requerimientos | G22: 10 de febrero de 2025 10:25:47 | H22: 200 | I22: Consumo | J22: 1 de abril de 2028 00:00:00 | K22: S/E Maipo 220kV | L22: 220 | M22: Barra GIS 1 y 2 | N22: J3 | O22: Metropolitana de Santiago | P22: Buin | Q22: Nacional
A23: 2515 | B23: Campo de Datos Lampa | C23: 5768 | D23: CI GMF II Patache ProjectCo SpA | E23: SAC | F23: Desarrollo de estudios y/o antecedentes | G23: 7 de mayo de 2025 17:29:33 | H23: 0 | I23: Consumo | J23: 31 de diciembre de 2029 00:00:00 | K23: Nueva Lampa 220kV | L23: 220 | M23: Interruptor y medio | N23: J18 y J21 | O23: Metropolitana de Santiago | P23: Lampa | Q23: Nacional

Sheet DC SEA  2026
Z1: MANO DE OBRA
K2: Grupo electrógeno | M2: total principal | P2: total respaldo | W2: total chiller | X2: total general GE PyR KW
A3: Nombre del Proyecto | B3: WEB | C3: Región | D3: Comuna | E3: Titular | F3: Inversión (MMU$) | G3: Estado del Proyecto | H3: Días DIA | I3: Fecha Calificación | J3: Empresa Consultora | K3: GE Salas (Principal) | L3: P Generada (KW) | M3: Total Generado KW | N3: GE Oficinas (Respaldo) | O3: P Generada (KW)2 | P3: Total Generado KW2 | Q3: Cantidad Diesel /L | R3: Cantidad Diesel /kg | S3: Ratio L/kg | T3: Vida util Años DC | U3: Cantidad Chillers | V3: Consumo (KW)3 | W3: Total consumo Chillers KW | X3: Total general GE PyR KW | Y3: Principal IT /1.5 | Z3: Promedio construcción | AA3: Máximo P construcción | AB3: Promedio Operación | AC3: Máximo P Operación | AD3: Promedio Cierre | AE3: Máximo P Cierre | AF3: MO Contrucción Promedio | AG3: MO Contrucción Máximo | AH3: MO Operación Promedio | AI3: MO Operación Máximo | AJ3: MO Cierre Promedio | AK3: MO Cierre Máximo | AL3: Latitud | AM3: Longitud | AN3: Superficie útil m2 | AO3: Superficie Bruta m2 | AP3: Empresa | AQ3: Proyectos | AR3: CAPEX (MMUSD)
A4: Centro de Almacenamiento de Datos Puente Alto | B4: Ver | C4: Metropolitana | D4: Puente Alto | E4: Inmobiliaria STPA SPA | F4: 0 | G4: Pendiente | H4: =+(Tabla35[[#This Row],[Fecha Calificación]]-TODAY())*-1 -> 31 | I4: 46265 | J4: Inmobiliaria STPA SPA | K4: 44 | L4: 2200 | M4: =Tabla35[[#This Row],[P Generada (KW)]]*Tabla35[[#This Row],[GE Salas (Principal)]] -> 96800 | N4: 2 | O4: 2200 | P4: =Tabla35[[#This Row],[P Generada (KW)2]]*Tabla35[[#This Row],[GE Oficinas (Respaldo)]] -> 4400 | Q4: 900450 | R4: 756000 | S4: =+Tabla35[[#This Row],[Cantidad Diesel /kg]]/Tabla35[[#This Row],[Cantidad Diesel /L]] -> 0.83958021 | U4: 120 | V4: 1600 | W4: =Tabla35[[#This Row],[Consumo (KW)3]]*Tabla35[[#This Row],[Cantidad Chillers]] -> 192000 | X4: =Tabla35[[#This Row],[Total consumo Chillers KW]]+Tabla35[[#This Row],[Total Generado KW2]]+Tabla35[[#This Row],[Total Generado KW]] -> 293200 | Y4: =Tabla35[[#This Row],[Total Generado KW]]/1.5 -> 64533.333 | Z4: =+Tabla35[[#This Row],[MO Contrucción Promedio]]/Tabla35[[#This Row],[Total Generado KW]] -> 0
A5: Centro de Almacenamiento de Datos San Antonio | B5: Ver | C5: Valparaíso | D5: San Antonio | E5: Nodo Pacífico SpA | F5: 262 | G5: Pendiente | H5: =+(Tabla35[[#This Row],[Fecha Calificación]]-TODAY())*-1 -> 3 | I5: 46293 | J5: Sustentable | K5: 32 | L5: 2578 | M5: =+Tabla35[[#This Row],[P Generada (KW)]]*Tabla35[[#This Row],[GE Salas (Principal)]] -> 82496 | N5: 2 | O5: =+Tabla35[[#This Row],[GE Oficinas (Respaldo)]]*Tabla35[[#This Row],[P Generada (KW)]] -> 5156 | P5: =Tabla35[[#This Row],[P Generada (KW)2]]*Tabla35[[#This Row],[GE Oficinas (Respaldo)]] -> 10312 | Q5: =+Tabla35[[#This Row],[Cantidad Diesel /kg]]/Tabla35[[#This Row],[Ratio L/kg]] -> 990000 | R5: 841500 | S5: 0.85 | W5: =Tabla35[[#This Row],[Consumo (KW)3]]*Tabla35[[#This Row],[Cantidad Chillers]] -> 0 | X5: =Tabla35[[#This Row],[Total consumo Chillers KW]]+Tabla35[[#This Row],[Total Generado KW2]]+Tabla35[[#This Row],[Total Generado KW]] -> 92808 | Y5: =Tabla35[[#This Row],[Total Generado KW]]/1.5 -> 54997.333 | Z5: =+Tabla35[[#This Row],[MO Contrucción Promedio]]/Tabla35[[#This Row],[Total Generado KW]] -> 0
A6: Data Center Polpaico Campus Norte | B6: Ver | C6: Metropolitana | D6: Til-til | E6: GR Culle SpA | F6: 25 | G6: Pendiente | H6: =+(Tabla35[[#This Row],[Fecha Calificación]]-TODAY())*-1 -> 16 | I6: 46280 | J6: Grenergy | K6: 60 | L6: 2800 | M6: =Tabla35[[#This Row],[P Generada (KW)]]*Tabla35[[#This Row],[GE Salas (Principal)]] -> 168000 | P6: =Tabla35[[#This Row],[P Generada (KW)2]]*Tabla35[[#This Row],[GE Oficinas (Respaldo)]] -> 0 | R6: <1000 | S6: =+Tabla35[[#This Row],[Cantidad Diesel /kg]]/Tabla35[[#This Row],[Cantidad Diesel /L]] -> #VALUE! | W6: =Tabla35[[#This Row],[Consumo (KW)3]]*Tabla35[[#This Row],[Cantidad Chillers]] -> 0 | X6: =Tabla35[[#This Row],[Total consumo Chillers KW]]+Tabla35[[#This Row],[Total Generado KW2]]+Tabla35[[#This Row],[Total Generado KW]] -> 168000 | Y6: =Tabla35[[#This Row],[Total Generado KW]]/1.5 -> 112000 | Z6: =+Tabla35[[#This Row],[MO Contrucción Promedio]]/Tabla35[[#This Row],[Total Generado KW]] -> 0
A7: Data Center Lo Aguirre | B7: =HYPERLINK("https://infofirma.sea.gob.cl/DocumentosSEA/MostrarDocumento?docId=2026/09/26/40d9-b957-46d4-b27d-350f082b2f28","Ver") -> Ver | C7: Metropolitana | D7: Pudahuel | E7: Lader Energy Chile SpA | F7: 25 | G7: Pendiente | H7: =+(Tabla35[[#This Row],[Fecha Calificación]]-TODAY())*-1 -> 68 | I7: 46228 | J7: Lader Energy Chile SpA | K7: 60 | L7: 2800 | M7: =Tabla35[[#This Row],[P Generada (KW)]]*Tabla35[[#This Row],[GE Salas (Principal)]] -> 168000 | P7: =Tabla35[[#This Row],[P Generada (KW)2]]*Tabla35[[#This Row],[GE Oficinas (Respaldo)]] -> 0 | Q7: 1164705 | R7: 990000 | S7: =+Tabla35[[#This Row],[Cantidad Diesel /kg]]/Tabla35[[#This Row],[Cantidad Diesel /L]] -> 0.85000064 | T7: 30 | W7: =Tabla35[[#This Row],[Consumo (KW)3]]*Tabla35[[#This Row],[Cantidad Chillers]] -> 0 | X7: =Tabla35[[#This Row],[Total consumo Chillers KW]]+Tabla35[[#This Row],[Total Generado KW2]]+Tabla35[[#This Row],[Total Generado KW]] -> 168000 | Y7: =Tabla35[[#This Row],[Total Generado KW]]/1.5 -> 112000 | Z7: =+Tabla35[[#This Row],[MO Contrucción Promedio]]/Tabla35[[#This Row],[Total Generado KW]] -> 0.0020833333 | AA7: =+Tabla35[[#This Row],[MO Contrucción Máximo]]/Tabla35[[#This Row],[Total Generado KW]] -> 0.0041666667 | AB7: =+Tabla35[[#This Row],[MO Operación Promedio]]/Tabla35[[#This Row],[Total Generado KW]] -> 0.00089285714 | AC7: =+Tabla35[[#This Row],[MO Operación Máximo]]/Tabla35[[#This Row],[Total Generado KW]] -> 0.0017857143 | AD7: =+Tabla35[[#This Row],[MO Cierre Promedio]]/Tabla35[[#This Row],[Total Generado KW]] -> 0.0020833333 | AE7: =+Tabla35[[#This Row],[MO Cierre Máximo]]/Tabla35[[#This Row],[Total Generado KW]] -> 0.0041666667 | AF7: 350 | AG7: 700 | AH7: 150 | AI7: 300 | AJ7: 350 | AK7: 700 | AL7: -70907931 | AM7: -33450639 | AN7: 83568 | AO7: 171373
A8: Data Center La Polvora | B8: =HYPERLINK("https://infofirma.sea.gob.cl/DocumentosSEA/MostrarDocumento?docId=2026/07/30/4984-cbee-46bd-816a-cfd384a6bbbf","Ver") -> Ver | C8: Valparaíso | D8: Valparaíso | E8: DCI LA POLVORA SpA | F8: 25 | G8: Pendiente | H8: =+(Tabla35[[#This Row],[Fecha Calificación]]-TODAY())*-1 -> 70 | I8: 46226 | J8: DCI Partners | K8: 54 | L8: 2800 | M8: =Tabla35[[#This Row],[P Generada (KW)]]*Tabla35[[#This Row],[GE Salas (Principal)]] -> 151200 | P8: =Tabla35[[#This Row],[P Generada (KW)2]]*Tabla35[[#This Row],[GE Oficinas (Respaldo)]] -> 0 | Q8: 1164705 | R8: 990000 | S8: =+Tabla35[[#This Row],[Cantidad Diesel /kg]]/Tabla35[[#This Row],[Cantidad Diesel /L]] -> 0.85000064 | W8: =Tabla35[[#This Row],[Consumo (KW)3]]*Tabla35[[#This Row],[Cantidad Chillers]] -> 0 | X8: =Tabla35[[#This Row],[Total consumo Chillers KW]]+Tabla35[[#This Row],[Total Generado KW2]]+Tabla35[[#This Row],[Total Generado KW]] -> 151200 | Y8: =Tabla35[[#This Row],[Total Generado KW]]/1.5 -> 100800 | Z8: =+Tabla35[[#This Row],[MO Contrucción Promedio]]/Tabla35[[#This Row],[Total Generado KW]] -> 0 | AA8: =+Tabla35[[#This Row],[MO Contrucción Máximo]]/Tabla35[[#This Row],[Total Generado KW]] -> 0.0031746032 | AB8: =+Tabla35[[#This Row],[MO Operación Promedio]]/Tabla35[[#This Row],[Total Generado KW]] -> 0 | AC8: =+Tabla35[[#This Row],[MO Operación Máximo]]/Tabla35[[#This Row],[Total Generado KW]] -> 0.0015873016 | AD8: =+Tabla35[[#This Row],[MO Cierre Promedio]]/Tabla35[[#This Row],[Total Generado KW]] -> 0 | AE8: =+Tabla35[[#This Row],[MO Cierre Máximo]]/Tabla35[[#This Row],[Total Generado KW]] -> 0 | AG8: 480 | AI8: 240 | AL8: -71619954514165 | AM8: -33086077367795 | AN8: 52000 | AO8: 66649
A9: Datacenter Terranova Alto Jahuel | B9: =HYPERLINK("https://infofirma.sea.gob.cl/DocumentosSEA/MostrarDocumento?docId=2026/05/05/aaf0-5d7c-4f7a-9163-f58684ca2a4a","Ver") -> Ver | C9: Metropolitana | D9: Buin | E9: DC Terranova | F9: 25 | G9: Pendiente | H9: =+(Tabla35[[#This Row],[Fecha Calificación]]-TODAY())*-1 -> 149 | I9: 46147 | J9: Sustentable | K9: 54 | L9: 2250 | M9: =Tabla35[[#This Row],[P Generada (KW)]]*Tabla35[[#This Row],[GE Salas (Principal)]] -> 121500 | N9: 2 | O9: 1100 | P9: =Tabla35[[#This Row],[P Generada (KW)2]]*Tabla35[[#This Row],[GE Oficinas (Respaldo)]] -> 2200 | Q9: 1164705 | R9: 990000 | S9: =+Tabla35[[#This Row],[Cantidad Diesel /kg]]/Tabla35[[#This Row],[Cantidad Diesel /L]] -> 0.85000064 | T9: Indefinida | W9: =Tabla35[[#This Row],[Consumo (KW)3]]*Tabla35[[#This Row],[Cantidad Chillers]] -> 0 | X9: =Tabla35[[#This Row],[Total consumo Chillers KW]]+Tabla35[[#This Row],[Total Generado KW2]]+Tabla35[[#This Row],[Total Generado KW]] -> 123700 | Y9: =Tabla35[[#This Row],[Total Generado KW]]/1.5 -> 81000 | Z9: =+Tabla35[[#This Row],[MO Contrucción Promedio]]/Tabla35[[#This Row],[Total Generado KW]] -> 0 | AA9: =+Tabla35[[#This Row],[MO Contrucción Máximo]]/Tabla35[[#This Row],[Total Generado KW]] -> 0.0032921811 | AB9: =+Tabla35[[#This Row],[MO Operación Promedio]]/Tabla35[[#This Row],[Total Generado KW]] -> 0 | AC9: =+Tabla35[[#This Row],[MO Operación Máximo]]/Tabla35[[#This Row],[Total Generado KW]] -> 0.002526749 | AD9: =+Tabla35[[#This Row],[MO Cierre Promedio]]/Tabla35[[#This Row],[Total Generado KW]] -> 0 | AE9: =+Tabla35[[#This Row],[MO Cierre Máximo]]/Tabla35[[#This Row],[Total Generado KW]] -> 0 | AG9: 400 | AI9: 307 | AL9: -33.7186 | AM9: -70.6912 | AN9: 32141.842 | AO9: 56200
A10: Campo de Datos Lampa | B10: =HYPERLINK("https://infofirma.sea.gob.cl/DocumentosSEA/MostrarDocumento?docId=2026/07/13/14d0-c32d-4f7a-9c8d-5ccb210b429f","Ver") -> Ver | C10: Metropolitana | D10: Lampa | E10: CI GMF II Chile DevCo I SpA | F10: 850 | G10: Pendiente | H10: =+(Tabla35[[#This Row],[Fecha Calificación]]-TODAY())*-1 -> 80 | I10: 46216 | J10: GIZA Ingeniería | K10: 45 | L10: 2500 | M10: =Tabla35[[#This Row],[P Generada (KW)]]*Tabla35[[#This Row],[GE Salas (Principal)]] -> 112500 | N10: 1 | O10: 1020 | P10: =Tabla35[[#This Row],[P Generada (KW)2]]*Tabla35[[#This Row],[GE Oficinas (Respaldo)]] -> 1020 | Q10: 601647 | R10: 511400 | S10: =+Tabla35[[#This Row],[Cantidad Diesel /kg]]/Tabla35[[#This Row],[Cantidad Diesel /L]] -> 0.85000008 | T10: Indefinida | U10: 90 | W10: =Tabla35[[#This Row],[Consumo (KW)3]]*Tabla35[[#This Row],[Cantidad Chillers]] -> 0 | X10: =Tabla35[[#This Row],[Total consumo Chillers KW]]+Tabla35[[#This Row],[Total Generado KW2]]+Tabla35[[#This Row],[Total Generado KW]] -> 113520 | Y10: =Tabla35[[#This Row],[Total Generado KW]]/1.5 -> 75000 | Z10: =+Tabla35[[#This Row],[MO Contrucción Promedio]]/Tabla35[[#This Row],[Total Generado KW]] -> 0 | AA10: =+Tabla35[[#This Row],[MO Contrucción Máximo]]/Tabla35[[#This Row],[Total Generado KW]] -> 0.0026666667 | AB10: =+Tabla35[[#This Row],[MO Operación Promedio]]/Tabla35[[#This Row],[Total Generado KW]] -> 0 | AC10: =+Tabla35[[#This Row],[MO Operación Máximo]]/Tabla35[[#This Row],[Total Generado KW]] -> 0.0013333333 | AD10: =+Tabla35[[#This Row],[MO Cierre Promedio]]/Tabla35[[#This Row],[Total Generado KW]] -> 0 | AE10: =+Tabla35[[#This Row],[MO Cierre Máximo]]/Tabla35[[#This Row],[Total Generado KW]] -> 0 | AG10: 300 | AI10: 150 | AL10: -7076770157877 | AM10: -33317910875209 | AN10: 39397.71 | AO10: 219476
A11: Data Center Alto Jahuel Campus Sur | B11: =HYPERLINK("https://infofirma.sea.gob.cl/DocumentosSEA/MostrarDocumento?docId=2026/05/29/d544-ae11-47d8-8e57-90e569bf78e3","Ver") -> Ver | C11: Metropolitana | D11: Buin | E11: GR Huiña SpA | F11: 20 | G11: Pendiente | H11: =+(Tabla35[[#This Row],[Fecha Calificación]]-TODAY())*-1 -> 125 | I11: 46171 | J11: Grenergy | K11: 48 | L11: 2800 | M11: =Tabla35[[#This Row],[P Generada (KW)]]*Tabla35[[#This Row],[GE Salas (Principal)]] -> 134400 | P11: =Tabla35[[#This Row],[P Generada (KW)2]]*Tabla35[[#This Row],[GE Oficinas (Respaldo)]] -> 0 | Q11: 1170588 | R11: 995000 | S11: =+Tabla35[[#This Row],[Cantidad Diesel /kg]]/Tabla35[[#This Row],[Cantidad Diesel /L]] -> 0.85000017 | T11: 30 | W11: =Tabla35[[#This Row],[Consumo (KW)3]]*Tabla35[[#This Row],[Cantidad Chillers]] -> 0 | X11: =Tabla35[[#This Row],[Total consumo Chillers KW]]+Tabla35[[#This Row],[Total Generado KW2]]+Tabla35[[#This Row],[Total Generado KW]] -> 134400 | Y11: =Tabla35[[#This Row],[Total Generado KW]]/1.5 -> 89600 | Z11: =+Tabla35[[#This Row],[MO Contrucción Promedio]]/Tabla35[[#This Row],[Total Generado KW]] -> 0 | AA11: =+Tabla35[[#This Row],[MO Contrucción Máximo]]/Tabla35[[#This Row],[Total Generado KW]] -> 0.0016369048 | AB11: =+Tabla35[[#This Row],[MO Operación Promedio]]/Tabla35[[#This Row],[Total Generado KW]] -> 0 | AC11: =+Tabla35[[#This Row],[MO Operación Máximo]]/Tabla35[[#This Row],[Total Generado KW]] -> 0.00081845238 | AD11: =+Tabla35[[#This Row],[MO Cierre Promedio]]/Tabla35[[#This Row],[Total Generado KW]] -> 0 | AE11: =+Tabla35[[#This Row],[MO Cierre Máximo]]/Tabla35[[#This Row],[Total Generado KW]] -> 0 | AG11: 220 | AI11: 110 | AL11: -33.707188 | AM11: -70.697045 | AN11: 58500 | AO11: 85275.48
A12: Datacenter ST5 | B12: Ver | C12: Metropolitana | D12: Pudahuel | E12: Equinix | F12: 130 | G12: Aprobado | H12: 367.72455 | I12: 45768.667 | J12: GIZA Ingeniería | K12: 16 | L12: 2800 | M12: =Tabla35[[#This Row],[P Generada (KW)]]*Tabla35[[#This Row],[GE Salas (Principal)]] -> 44800 | N12: 1 | O12: 720 | P12: =Tabla35[[#This Row],[P Generada (KW)2]]*Tabla35[[#This Row],[GE Oficinas (Respaldo)]] -> 720 | Q12: 337500 | R12: 286875 | S12: =+Tabla35[[#This Row],[Cantidad Diesel /kg]]/Tabla35[[#This Row],[Cantidad Diesel /L]] -> 0.85 | T12: 33,5 | U12: 28 | V12: 1420 | W12: =Tabla35[[#This Row],[Consumo (KW)3]]*Tabla35[[#This Row],[Cantidad Chillers]] -> 39760 | X12: =Tabla35[[#This Row],[Total Generado KW]]+Tabla35[[#This Row],[Total Generado KW2]] -> 45520 | Y12: =Tabla35[[#This Row],[Total Generado KW]]/1.5 -> 29866.667 | Z12: =+Tabla35[[#This Row],[MO Contrucción Promedio]]/Tabla35[[#This Row],[Total Generado KW]] -> 0.0020089286 | AA12: =+Tabla35[[#This Row],[MO Contrucción Máximo]]/Tabla35[[#This Row],[Total Generado KW]] -> 0.0040178571 | AB12: =+Tabla35[[#This Row],[MO Operación Promedio]]/Tabla35[[#This Row],[Total Generado KW]] -> 0.00089285714 | AC12: =+Tabla35[[#This Row],[MO Operación Máximo]]/Tabla35[[#This Row],[Total Generado KW]] -> 0.0013392857 | AD12: =+Tabla35[[#This Row],[MO Cierre Promedio]]/Tabla35[[#This Row],[Total Generado KW]] -> 0.00044642857 | AE12: =+Tabla35[[#This Row],[MO Cierre Máximo]]/Tabla35[[#This Row],[Total Generado KW]] -> 0.00089285714 | AF12: 90 | AG12: 180 | AH12: 40 | AI12: 60 | AJ12: 20 | AK12: 40 | AL12: -33.438927 | AM12: -70.785885 | AN12: 24418 | AO12: 42409 | AP12: Equinix | AQ12: =+COUNTIFS(Tabla35[Titular],AP12,Tabla35[Estado del Proyecto],"Aprobado") -> 2 | AR12: =+SUMIFS(Tabla35[Inversión (MMU$)],Tabla35[Titular],AP12,Tabla35[Estado del Proyecto],"Aprobado") -> 174
A13: Ampliación Data Center Campus Scala Huechuraba | B13: Ver | C13: Metropolitana | D13: Huechuraba | E13: SCALA | F13: 145.2 | G13: Aprobado | H13: 167.82309 | I13: 45705.625 | J13: IT Ambiental | K13: 16 | L13: 2800 | M13: 33925 | N13: 3 | O13: 616 | P13: =Tabla35[[#This Row],[P Generada (KW)2]]*Tabla35[[#This Row],[GE Oficinas (Respaldo)]] -> 1848 | Q13: 300000 | R13: 255000 | S13: =+Tabla35[[#This Row],[Cantidad Diesel /kg]]/Tabla35[[#This Row],[Cantidad Diesel /L]] -> 0.85 | T13: Indefinida | U13: 14 | V13: 1560 | W13: =Tabla35[[#This Row],[Consumo (KW)3]]*Tabla35[[#This Row],[Cantidad Chillers]] -> 21840 | X13: =Tabla35[[#This Row],[Total Generado KW]]+Tabla35[[#This Row],[Total Generado KW2]] -> 35773 | Y13: =Tabla35[[#This Row],[Total Generado KW]]/1.5 -> 22616.667 | Z13: =+Tabla35[[#This Row],[MO Contrucción Promedio]]/Tabla35[[#This Row],[Total Generado KW]] -> 0.0044215181 | AA13: =+Tabla35[[#This Row],[MO Contrucción Máximo]]/Tabla35[[#This Row],[Total Generado KW]] -> 0.0088430361 | AB13: =+Tabla35[[#This Row],[MO Operación Promedio]]/Tabla35[[#This Row],[Total Generado KW]] -> 0.0026529108 | AC13: =+Tabla35[[#This Row],[MO Operación Máximo]]/Tabla35[[#This Row],[Total Generado KW]] -> 0.0029476787 | AD13: =+Tabla35[[#This Row],[MO Cierre Promedio]]/Tabla35[[#This Row],[Total Generado KW]] -> 0.0013264554 | AE13: =+Tabla35[[#This Row],[MO Cierre Máximo]]/Tabla35[[#This Row],[Total Generado KW]] -> 0.0014738394 | AF13: 150 | AG13: 300 | AH13: 90 | AI13: 100 | AJ13: 45 | AK13: 50 | AL13: -33.366358 | AM13: -70.673941 | AN13: 30197.78 | AO13: 38778 | AP13: SCALA | AQ13: =+COUNTIFS(Tabla35[Titular],AP13,Tabla35[Estado del Proyecto],"Aprobado") -> 4 | AR13: =+SUMIFS(Tabla35[Inversión (MMU$)],Tabla35[Titular],AP13,Tabla35[Estado del Proyecto],"Aprobado") -> 873.2
A14: Ampliación Data Center Campus Scala Huechuraba | B14: Ver | C14: Valparaíso | D14: Valparaíso | E14: SCALA | F14: 290 | G14: Aprobado | H14: 382.0183 | I14: 45636.625 | J14: IT Ambiental | K14: 30 | L14: 2750 | M14: =Tabla35[[#This Row],[P Generada (KW)]]*Tabla35[[#This Row],[GE Salas (Principal)]] -> 82500 | N14: 5 | O14: 400 | P14: =Tabla35[[#This Row],[P Generada (KW)2]]*Tabla35[[#This Row],[GE Oficinas (Respaldo)]] -> 2000 | Q14: 1090000 | R14: 926500 | S14: =+Tabla35[[#This Row],[Cantidad Diesel /kg]]/Tabla35[[#This Row],[Cantidad Diesel /L]] -> 0.85 | T14: Indefinida | U14: 25 | V14: 1550 | W14: =Tabla35[[#This Row],[Consumo (KW)3]]*Tabla35[[#This Row],[Cantidad Chillers]] -> 38750 | X14: =Tabla35[[#This Row],[Total Generado KW]]+Tabla35[[#This Row],[Total Generado KW2]] -> 84500 | Y14: =Tabla35[[#This Row],[Total Generado KW]]/1.5 -> 55000 | Z14: =+Tabla35[[#This Row],[MO Contrucción Promedio]]/Tabla35[[#This Row],[Total Generado KW]] -> 0.0043636364 | AA14: =+Tabla35[[#This Row],[MO Contrucción Máximo]]/Tabla35[[#This Row],[Total Generado KW]] -> 0.0072727273 | AB14: =+Tabla35[[#This Row],[MO Operación Promedio]]/Tabla35[[#This Row],[Total Generado KW]] -> 0.00063030303 | AC14: =+Tabla35[[#This Row],[MO Operación Máximo]]/Tabla35[[#This Row],[Total Generado KW]] -> 0.0012363636 | AD14: =+Tabla35[[#This Row],[MO Cierre Promedio]]/Tabla35[[#This Row],[Total Generado KW]] -> 0.00024242424 | AE14: =+Tabla35[[#This Row],[MO Cierre Máximo]]/Tabla35[[#This Row],[Total Generado KW]] -> 0.00048484848 | AF14: 360 | AG14: 600 | AH14: 52 | AI14: 102 | AJ14: 20 | AK14: 40 | AL14: -33.13749 | AM14: -71.55948 | AN14: 33302 | AO14: 82448 | AP14: EdgeConnex | AQ14: =+COUNTIFS(Tabla35[Titular],AP14,Tabla35[Estado del Proyecto],"Aprobado") -> 3 | AR14: =+SUMIFS(Tabla35[Inversión (MMU$)],Tabla35[Titular],AP14,Tabla35[Estado del Proyecto],"Aprobado") -> 213
A15: Data Center SCL04 | B15: Ver | C15: Metropolitana | D15: Colina | E15: EdgeConnex | F15: 40 | G15: Aprobado | H15: 307.92259 | I15: 45468.667 | J15: GIZA Ingeniería | K15: 18 | L15: 3000 | M15: =Tabla35[[#This Row],[P Generada (KW)]]*Tabla35[[#This Row],[GE Salas (Principal)]] -> 54000 | N15: 3 | O15: 3000 | P15: =Tabla35[[#This Row],[P Generada (KW)2]]*Tabla35[[#This Row],[GE Oficinas (Respaldo)]] -> 9000 | Q15: 933555 | R15: 1098300 | S15: =+Tabla35[[#This Row],[Cantidad Diesel /kg]]/Tabla35[[#This Row],[Cantidad Diesel /L]] -> 1.1764706 | T15: 27 | U15: 42 | V15: No se especifica | W15: 0 | X15: =Tabla35[[#This Row],[Total Generado KW]]+Tabla35[[#This Row],[Total Generado KW2]] -> 63000 | Y15: =Tabla35[[#This Row],[Total Generado KW]]/1.5 -> 36000 | Z15: =+Tabla35[[#This Row],[MO Contrucción Promedio]]/Tabla35[[#This Row],[Total Generado KW]] -> 0.002 | AA15: =+Tabla35[[#This Row],[MO Contrucción Máximo]]/Tabla35[[#This Row],[Total Generado KW]] -> 0.0033333333 | AB15: =+Tabla35[[#This Row],[MO Operación Promedio]]/Tabla35[[#This Row],[Total Generado KW]] -> 0.0013888889 | AC15: =+Tabla35[[#This Row],[MO Operación Máximo]]/Tabla35[[#This Row],[Total Generado KW]] -> 0.0027777778 | AD15: =+Tabla35[[#This Row],[MO Cierre Promedio]]/Tabla35[[#This Row],[Total Generado KW]] -> 0.00037037037 | AE15: =+Tabla35[[#This Row],[MO Cierre Máximo]]/Tabla35[[#This Row],[Total Generado KW]] -> 0.00074074074 | AF15: 108 | AG15: 180 | AH15: 75 | AI15: 150 | AJ15: 20 | AK15: 40 | AL15: -33.297771 | AM15: -70.705801 | AN15: 34200 | AO15: 65000 | AP15: Cirion | AQ15: =+COUNTIFS(Tabla35[Titular],AP15,Tabla35[Estado del Proyecto],"Aprobado") -> 1 | AR15: =+SUMIFS(Tabla35[Inversión (MMU$)],Tabla35[Titular],AP15,Tabla35[Estado del Proyecto],"Aprobado") -> 120
A16: Data Center Cirion | B16: Ver | C16: Metropolitana | D16: Quilicura | E16: Cirion | F16: 120 | G16: Aprobado | H16: 236.83172 | I16: 45313.625 | J16: GIZA Ingeniería | K16: 16 | L16: 1850 | M16: =Tabla35[[#This Row],[P Generada (KW)]]*Tabla35[[#This Row],[GE Salas (Principal)]] -> 29600 | N16: 0 | O16: 0 | P16: =Tabla35[[#This Row],[P Generada (KW)2]]*Tabla35[[#This Row],[GE Oficinas (Respaldo)]] -> 0 | Q16: 400000 | R16: 340000 | S16: =+Tabla35[[#This Row],[Cantidad Diesel /kg]]/Tabla35[[#This Row],[Cantidad Diesel /L]] -> 0.85 | T16: 27 | U16: No se especifica | V16: No se especifica | X16: =Tabla35[[#This Row],[Total Generado KW]]+Tabla35[[#This Row],[Total Generado KW2]] -> 29600 | Y16: =Tabla35[[#This Row],[Total Generado KW]]/1.5 -> 19733.333 | Z16: =+Tabla35[[#This Row],[MO Contrucción Promedio]]/Tabla35[[#This Row],[Total Generado KW]] -> 0.0036486486 | AA16: =+Tabla35[[#This Row],[MO Contrucción Máximo]]/Tabla35[[#This Row],[Total Generado KW]] -> 0.0060810811 | AB16: =+Tabla35[[#This Row],[MO Operación Promedio]]/Tabla35[[#This Row],[Total Generado KW]] -> 0.00067567568 | AC16: =+Tabla35[[#This Row],[MO Operación Máximo]]/Tabla35[[#This Row],[Total Generado KW]] -> 0.0013513514 | AD16: =+Tabla35[[#This Row],[MO Cierre Promedio]]/Tabla35[[#This Row],[Total Generado KW]] -> 0.00067567568 | AE16: =+Tabla35[[#This Row],[MO Cierre Máximo]]/Tabla35[[#This Row],[Total Generado KW]] -> 0.0013513514 | AF16: 108 | AG16: 180 | AH16: 20 | AI16: 40 | AJ16: 20 | AK16: 40 | AL16: -33.356811 | AM16: -70.69955 | AP16: Amazon | AQ16: =+COUNTIFS(Tabla35[Titular],AP16,Tabla35[Estado del Proyecto],"Aprobado") -> 2 | AR16: =+SUMIFS(Tabla35[Inversión (MMU$)],Tabla35[Titular],AP16,Tabla35[Estado del Proyecto],"Aprobado") -> 410
A17: Centro de Almacenamiento de Datos Huechuraba | B17: Ver | C17: Metropolitana | D17: Huechuraba | E17: Amazon | F17: 205 | G17: Aprobado | H17: 527.10205 | I17: 45471.667 | J17: ORBE Consultores | K17: 20 | L17: 2800 | M17: =Tabla35[[#This Row],[P Generada (KW)]]*Tabla35[[#This Row],[GE Salas (Principal)]] -> 56000 | N17: 1 | O17: 1800 | P17: =+Tabla35[[#This Row],[P Generada (KW)2]]*Tabla35[[#This Row],[GE Oficinas (Respaldo)]] -> 1800 | Q17: 426224 | R17: 358028 | S17: =+Tabla35[[#This Row],[Cantidad Diesel /kg]]/Tabla35[[#This Row],[Cantidad Diesel /L]] -> 0.83999962 | T17: 30 | U17: No se especifica | V17: No se especifica | X17: =Tabla35[[#This Row],[Total Generado KW]]+Tabla35[[#This Row],[Total Generado KW2]] -> 57800 | Y17: =Tabla35[[#This Row],[Total Generado KW]]/1.5 -> 37333.333 | AF17: 245 | AG17: 310 | AH17: 50 | AI17: 50 | AJ17: 40 | AK17: 40 | AL17: -33.366358 | AM17: -70.673941 | AP17: Ascenty | AQ17: =+COUNTIFS(Tabla35[Titular],AP17,Tabla35[Estado del Proyecto],"Aprobado") -> 2 | AR17: =+SUMIFS(Tabla35[Inversión (MMU$)],Tabla35[Titular],AP17,Tabla35[Estado del Proyecto],"Aprobado") -> 220
A18: Centro de Almacenamiento de Datos Padre Hurtado | B18: Ver | C18: Metropolitana | D18: Padre Hurtado | E18: Amazon | F18: 205 | G18: Aprobado | H18: 473.82668 | I18: 45300.625 | J18: ORBE Consultores | K18: 10 | L18: 2800 | M18: =Tabla35[[#This Row],[P Generada (KW)]]*Tabla35[[#This Row],[GE Salas (Principal)]] -> 28000 | N18: 1 | O18: 1050 | P18: =+Tabla35[[#This Row],[P Generada (KW)2]]*Tabla35[[#This Row],[GE Oficinas (Respaldo)]] -> 1050 | Q18: 216205 | R18: 179883 | S18: =+Tabla35[[#This Row],[Cantidad Diesel /kg]]/Tabla35[[#This Row],[Cantidad Diesel /L]] -> 0.83200204 | T18: 30 | U18: No se especifica | V18: No se especifica | X18: =Tabla35[[#This Row],[Total Generado KW]]+Tabla35[[#This Row],[Total Generado KW2]] -> 29050 | Y18: =Tabla35[[#This Row],[Total Generado KW]]/1.5 -> 18666.667 | AF18: 245 | AG18: 310 | AH18: 25 | AI18: 25 | AJ18: 40 | AK18: 40 | AL18: -33.373394 | AM18: -70.660089 | AP18: ODATA | AQ18: =+COUNTIFS(Tabla35[Titular],AP18,Tabla35[Estado del Proyecto],"Aprobado") -> 1 | AR18: =+SUMIFS(Tabla35[Inversión (MMU$)],Tabla35[Titular],AP18,Tabla35[Estado del Proyecto],"Aprobado") -> 271
A19: Centro de Almacenamiento de Datos Puente Alto | B19: Ver | C19: Metropolitana | D19: Puente Alto | E19: Amazon | F19: 205 | G19: Desistido | H19: 179.7812 | I19: 44956.625 | J19: ORBE Consultores | K19: 20 | L19: 2800 | M19: =Tabla35[[#This Row],[P Generada (KW)]]*Tabla35[[#This Row],[GE Salas (Principal)]] -> 56000 | N19: 1 | O19: 1800 | P19: =+Tabla35[[#This Row],[P Generada (KW)2]]*Tabla35[[#This Row],[GE Oficinas (Respaldo)]] -> 1800 | Q19: 426224 | R19: 358028 | S19: =+Tabla35[[#This Row],[Cantidad Diesel /kg]]/Tabla35[[#This Row],[Cantidad Diesel /L]] -> 0.83999962 | T19: 30 | U19: No se especifica | V19: No se especifica | X19: =Tabla35[[#This Row],[Total Generado KW]]+Tabla35[[#This Row],[Total Generado KW2]] -> 57800 | Y19: =Tabla35[[#This Row],[Total Generado KW]]/1.5 -> 37333.333 | AF19: 245 | AG19: 310 | AH19: 25 | AI19: 25 | AJ19: 40 | AK19: 40 | AL19: -33.556681 | AM19: -70.813233
A20: Scala Data Center Curauma | B20: Ver | C20: Valparaíso | D20: Valparaíso | E20: SCALA | F20: 65 | G20: Aprobado | H20: 177.81226 | I20: 44816.625 | J20: GIZA Ingeniería | K20: 6 | L20: 2750 | M20: =Tabla35[[#This Row],[P Generada (KW)]]*Tabla35[[#This Row],[GE Salas (Principal)]] -> 16500 | N20: 1 | O20: 400 | P20: =Tabla35[[#This Row],[P Generada (KW)2]]*Tabla35[[#This Row],[GE Oficinas (Respaldo)]] -> 400 | Q20: 218000 | R20: 185300 | S20: =+Tabla35[[#This Row],[Cantidad Diesel /kg]]/Tabla35[[#This Row],[Cantidad Diesel /L]] -> 0.85 | T20: 25 | U20: 5 | V20: 1550 | W20: =Tabla35[[#This Row],[Consumo (KW)3]]*Tabla35[[#This Row],[Cantidad Chillers]] -> 7750 | X20: =Tabla35[[#This Row],[Total Generado KW]]+Tabla35[[#This Row],[Total Generado KW2]] -> 16900 | Y20: =Tabla35[[#This Row],[Total Generado KW]]/1.5 -> 11000 | Z20: =+Tabla35[[#This Row],[MO Contrucción Promedio]]/Tabla35[[#This Row],[Total Generado KW]] -> 0.0072727273 | AA20: =+Tabla35[[#This Row],[MO Contrucción Máximo]]/Tabla35[[#This Row],[Total Generado KW]] -> 0.012121212 | AB20: =+Tabla35[[#This Row],[MO Operación Promedio]]/Tabla35[[#This Row],[Total Generado KW]] -> 0.00060606061 | AC20: =+Tabla35[[#This Row],[MO Operación Máximo]]/Tabla35[[#This Row],[Total Generado KW]] -> 0.0012121212 | AD20: =+Tabla35[[#This Row],[MO Cierre Promedio]]/Tabla35[[#This Row],[Total Generado KW]] -> 0.0012121212 | AE20: =+Tabla35[[#This Row],[MO Cierre Máximo]]/Tabla35[[#This Row],[Total Generado KW]] -> 0.0024242424 | AF20: 120 | AG20: 200 | AH20: 10 | AI20: 20 | AJ20: 20 | AK20: 40 | AL20: -33.135973 | AM20: -71.558861 | AP20: Sonda S.A. | AQ20: =+COUNTIFS(Tabla35[Titular],AP20,Tabla35[Estado del Proyecto],"Aprobado") -> 1 | AR20: =+SUMIFS(Tabla35[Inversión (MMU$)],Tabla35[Titular],AP20,Tabla35[Estado del Proyecto],"Aprobado") -> 125
A21: Scala Data Center Curauma | B21: Ver | C21: Valparaíso | D21: Valparaíso | E21: SCALA | F21: PEND | G21: 4 etapas | I21: 44816.625 | J21: GIZA Ingeniería | K21: 34 | L21: 2750 | M21: =Tabla35[[#This Row],[P Generada (KW)]]*Tabla35[[#This Row],[GE Salas (Principal)]] -> 93500 | N21: 4 | O21: 400 | P21: =Tabla35[[#This Row],[P Generada (KW)2]]*Tabla35[[#This Row],[GE Oficinas (Respaldo)]] -> 1600 | Q21: 1222000 | R21: 1038700 | S21: =+Tabla35[[#This Row],[Cantidad Diesel /kg]]/Tabla35[[#This Row],[Cantidad Diesel /L]] -> 0.85 | T21: 25 | U21: 30 | V21: 1550 | W21: =Tabla35[[#This Row],[Consumo (KW)3]]*Tabla35[[#This Row],[Cantidad Chillers]] -> 46500 | X21: =Tabla35[[#This Row],[Total Generado KW]]+Tabla35[[#This Row],[Total Generado KW2]] -> 95100 | Y21: =Tabla35[[#This Row],[Total Generado KW]]/1.5 -> 62333.333 | AL21: 33.137984 | AM21: -71.560931 | AP21: Dataluna | AQ21: 3 | AR21: =+SUMIFS(Tabla35[Inversión (MMU$)],Tabla35[Titular],AP21,Tabla35[Estado del Proyecto],"Aprobado")+H30 -> 358.16522
A22: Data Center SCL02-SCL03 | B22: Ver | C22: Metropolitana | D22: Colina | E22: EdgeConnex | F22: 73 | G22: Aprobado | H22: 192.88954 | I22: 44809.667 | J22: GIZA Ingeniería | K22: 64 | L22: 1000 | M22: =Tabla35[[#This Row],[P Generada (KW)]]*Tabla35[[#This Row],[GE Salas (Principal)]] -> 64000 | N22: 0 | O22: 0 | P22: =Tabla35[[#This Row],[P Generada (KW)2]]*Tabla35[[#This Row],[GE Oficinas (Respaldo)]] -> 0 | Q22: 736726 | R22: 612956 | S22: =+Tabla35[[#This Row],[Cantidad Diesel /kg]]/Tabla35[[#This Row],[Cantidad Diesel /L]] -> 0.83199996 | T22: 27 | U22: No se especifica | V22: No se especifica | X22: =Tabla35[[#This Row],[Total Generado KW]]+Tabla35[[#This Row],[Total Generado KW2]] -> 64000 | Y22: =Tabla35[[#This Row],[Total Generado KW]]/1.5 -> 42666.667 | Z22: =+Tabla35[[#This Row],[MO Contrucción Promedio]]/Tabla35[[#This Row],[Total Generado KW]] -> 0.0003125 | AA22: =+Tabla35[[#This Row],[MO Contrucción Máximo]]/Tabla35[[#This Row],[Total Generado KW]] -> 0.000625 | AB22: =+Tabla35[[#This Row],[MO Operación Promedio]]/Tabla35[[#This Row],[Total Generado KW]] -> 0.0003125 | AC22: =+Tabla35[[#This Row],[MO Operación Máximo]]/Tabla35[[#This Row],[Total Generado KW]] -> 0.000625 | AD22: =+Tabla35[[#This Row],[MO Cierre Promedio]]/Tabla35[[#This Row],[Total Generado KW]] -> 0.0003125 | AE22: =+Tabla35[[#This Row],[MO Cierre Máximo]]/Tabla35[[#This Row],[Total Generado KW]] -> 0.000625 | AF22: 20 | AG22: 40 | AH22: 20 | AI22: 40 | AJ22: 20 | AK22: 40 | AL22: -33.297339 | AM22: -70.705881 | AP22: CLARO CHILE S.A. | AQ22: =+COUNTIFS(Tabla35[Titular],AP22,Tabla35[Estado del Proyecto],"Aprobado") -> 1 | AR22: =+SUMIFS(Tabla35[Inversión (MMU$)],Tabla35[Titular],AP22,Tabla35[Estado del Proyecto],"Aprobado") -> 85
A23: SCALA DATA CENTER CAMPUS | B23: Ver | C23: Metropolitana | D23: Lampa | E23: SCALA | F23: 373 | G23: Aprobado | H23: 296.95604 | I23: 44746.625 | J23: GIZA Ingeniería | K23: 63 | L23: 2600 | M23: =Tabla35[[#This Row],[P Generada (KW)]]*Tabla35[[#This Row],[GE Salas (Principal)]] -> 163800 | N23: 2 | O23: 400 | P23: =Tabla35[[#This Row],[P Generada (KW)2]]*Tabla35[[#This Row],[GE Oficinas (Respaldo)]] -> 800 | Q23: 2215000 | R23: 1882750 | S23: =+Tabla35[[#This Row],[Cantidad Diesel /kg]]/Tabla35[[#This Row],[Cantidad Diesel /L]] -> 0.85 | T23: 30 | U23: 60 | V23: 1550 | W23: =Tabla35[[#This Row],[Consumo (KW)3]]*Tabla35[[#This Row],[Cantidad Chillers]] -> 93000 | X23: =Tabla35[[#This Row],[Total Generado KW]]+Tabla35[[#This Row],[Total Generado KW2]] -> 164600 | Y23: =Tabla35[[#This Row],[Total Generado KW]]/1.5 -> 109200 | Z23: =+Tabla35[[#This Row],[MO Contrucción Promedio]]/Tabla35[[#This Row],[Total Generado KW]] -> 0.00091575092 | AA23: =+Tabla35[[#This Row],[MO Contrucción Máximo]]/Tabla35[[#This Row],[Total Generado KW]] -> 0.0018315018 | AB23: =+Tabla35[[#This Row],[MO Operación Promedio]]/Tabla35[[#This Row],[Total Generado KW]] -> 0.00030525031 | AC23: =+Tabla35[[#This Row],[MO Operación Máximo]]/Tabla35[[#This Row],[Total Generado KW]] -> 0.00087912088 | AD23: =+Tabla35[[#This Row],[MO Cierre Promedio]]/Tabla35[[#This Row],[Total Generado KW]] -> 0.00030525031 | AE23: =+Tabla35[[#This Row],[MO Cierre Máximo]]/Tabla35[[#This Row],[Total Generado KW]] -> 0.00061050061 | AF23: 150 | AG23: 300 | AH23: 50 | AI23: 144 | AJ23: 50 | AK23: 100 | AL23: -33.292982 | AM23: -70.73915 | AP23: Digital holdings chile spa | AQ23: =+COUNTIFS(Tabla35[Titular],AP23,Tabla35[Estado del Proyecto],"Aprobado") -> 1 | AR23: =+SUMIFS(Tabla35[Inversión (MMU$)],Tabla35[Titular],AP23,Tabla35[Estado del Proyecto],"Aprobado") -> 31
A24: Data Center EDCSCL01 | B24: Ver | C24: Metropolitana | D24: Colina | E24: EdgeConnex | F24: 100 | G24: Aprobado | H24: 159.66245 | I24: 44585.625 | J24: GIZA Ingeniería | K24: 16 | L24: 880 | M24: =Tabla35[[#This Row],[P Generada (KW)]]*Tabla35[[#This Row],[GE Salas (Principal)]] -> 14080 | N24: 0 | O24: 0 | P24: =Tabla35[[#This Row],[P Generada (KW)2]]*Tabla35[[#This Row],[GE Oficinas (Respaldo)]] -> 0 | Q24: 184182 | R24: 153239 | S24: =+Tabla35[[#This Row],[Cantidad Diesel /kg]]/Tabla35[[#This Row],[Cantidad Diesel /L]] -> 0.8319977 | T24: Indefinida | U24: No se especifica | V24: No se especifica | X24: =Tabla35[[#This Row],[Total Generado KW]]+Tabla35[[#This Row],[Total Generado KW2]] -> 14080 | Y24: =Tabla35[[#This Row],[Total Generado KW]]/1.5 -> 9386.6667 | AB24: =+Tabla35[[#This Row],[MO Operación Promedio]]/Tabla35[[#This Row],[Total Generado KW]] -> 0.00071022727 | AC24: =+Tabla35[[#This Row],[MO Operación Máximo]]/Tabla35[[#This Row],[Total Generado KW]] -> 0.0012073864 | AD24: =+Tabla35[[#This Row],[MO Cierre Promedio]]/Tabla35[[#This Row],[Total Generado KW]] -> 0.0014204545 | AE24: =+Tabla35[[#This Row],[MO Cierre Máximo]]/Tabla35[[#This Row],[Total Generado KW]] -> 0.0028409091 | AF24: 0 | AG24: 0 | AH24: 10 | AI24: 17 | AJ24: 20 | AK24: 40 | AL24: -33.297023 | AM24: -70.703233 | AP24: TOTAL | AQ24: =+SUM(AQ12:AQ23) -> 21 | AR24: =+SUM(AR12:AR23) -> 2880.3652
A25: Data Center EDCSCL11 | B25: Ver | C25: Metropolitana | D25: San Bernardo | E25: EdgeConnex | F25: 250 | G25: Desistido | H25: 73.031123 | I25: 44473.625 | J25: GIZA Ingeniería | K25: 32 | L25: 2600 | M25: =Tabla35[[#This Row],[P Generada (KW)]]*Tabla35[[#This Row],[GE Salas (Principal)]] -> 83200 | N25: 2 | O25: 1500 | P25: =Tabla35[[#This Row],[P Generada (KW)2]]*Tabla35[[#This Row],[GE Oficinas (Respaldo)]] -> 3000 | Q25: 626484 | R25: 538537 | S25: =+Tabla35[[#This Row],[Cantidad Diesel /kg]]/Tabla35[[#This Row],[Cantidad Diesel /L]] -> 0.85961812 | T25: 25 | U25: No se especifica | V25: No se especifica | X25: =Tabla35[[#This Row],[Total Generado KW]]+Tabla35[[#This Row],[Total Generado KW2]] -> 86200 | Y25: =Tabla35[[#This Row],[Total Generado KW]]/1.5 -> 55466.667 | Z25: =+Tabla35[[#This Row],[MO Contrucción Promedio]]/Tabla35[[#This Row],[Total Generado KW]] -> 0.0012019231 | AA25: =+Tabla35[[#This Row],[MO Contrucción Máximo]]/Tabla35[[#This Row],[Total Generado KW]] -> 0.0024038462 | AB25: =+Tabla35[[#This Row],[MO Operación Promedio]]/Tabla35[[#This Row],[Total Generado KW]] -> 0.00024038462 | AC25: =+Tabla35[[#This Row],[MO Operación Máximo]]/Tabla35[[#This Row],[Total Generado KW]] -> 0.00048076923 | AD25: =+Tabla35[[#This Row],[MO Cierre Promedio]]/Tabla35[[#This Row],[Total Generado KW]] -> 0.00024038462 | AE25: =+Tabla35[[#This Row],[MO Cierre Máximo]]/Tabla35[[#This Row],[Total Generado KW]] -> 0.00048076923 | AF25: 100 | AG25: 200 | AH25: 20 | AI25: 40 | AJ25: 20 | AK25: 40 | AL25: -33.532519 | AM25: -70.712123
A26: Data Center Chile 2 | B26: Ver | C26: Metropolitana | D26: Quilicura | E26: Ascenty | F26: 150 | G26: Aprobado | H26: 133.86081 | I26: 44369.667 | J26: GIZA Ingeniería | K26: 30 | L26: 1800 | M26: =Tabla35[[#This Row],[P Generada (KW)]]*Tabla35[[#This Row],[GE Salas (Principal)]] -> 54000 | N26: 0 | O26: 0 | P26: =Tabla35[[#This Row],[P Generada (KW)2]]*Tabla35[[#This Row],[GE Oficinas (Respaldo)]] -> 0 | Q26: 796875 | R26: 663000 | S26: =+Tabla35[[#This Row],[Cantidad Diesel /kg]]/Tabla35[[#This Row],[Cantidad Diesel /L]] -> 0.832 | T26: 25 | U26: 24 | V26: 700 | W26: =Tabla35[[#This Row],[Consumo (KW)3]]*Tabla35[[#This Row],[Cantidad Chillers]] -> 16800 | X26: =Tabla35[[#This Row],[Total Generado KW]]+Tabla35[[#This Row],[Total Generado KW2]] -> 54000 | Y26: =Tabla35[[#This Row],[Total Generado KW]]/1.5 -> 36000 | AF26: 200 | AG26: 400 | AH26: 25 | AI26: 50 | AJ26: 20 | AK26: 45 | AL26: -33.33728 | AM26: -70.705939
A27: Data Center Ascenty | B27: Ver | C27: Metropolitana | D27: Quilicura | E27: Ascenty | F27: 70 | G27: Aprobado | H27: 198.80412 | I27: 44224.625 | J27: MHO Consultores | K27: 9 | L27: 2000 | M27: =Tabla35[[#This Row],[P Generada (KW)]]*Tabla35[[#This Row],[GE Salas (Principal)]] -> 18000 | N27: 0 | O27: 0 | P27: =Tabla35[[#This Row],[P Generada (KW)2]]*Tabla35[[#This Row],[GE Oficinas (Respaldo)]] -> 0 | Q27: 239062 | R27: 198900 | S27: =+Tabla35[[#This Row],[Cantidad Diesel /kg]]/Tabla35[[#This Row],[Cantidad Diesel /L]] -> 0.83200174 | T27: 20 | U27: 7 | V27: 700 | W27: =Tabla35[[#This Row],[Consumo (KW)3]]*Tabla35[[#This Row],[Cantidad Chillers]] -> 4900 | X27: =Tabla35[[#This Row],[Total Generado KW]]+Tabla35[[#This Row],[Total Generado KW2]] -> 18000 | Y27: =Tabla35[[#This Row],[Total Generado KW]]/1.5 -> 12000 | Z27: =+Tabla35[[#This Row],[MO Contrucción Promedio]]/Tabla35[[#This Row],[Total Generado KW]] -> 0.016666667 | AA27: =+Tabla35[[#This Row],[MO Contrucción Máximo]]/Tabla35[[#This Row],[Total Generado KW]] -> 0.016666667 | AB27: =+Tabla35[[#This Row],[MO Operación Promedio]]/Tabla35[[#This Row],[Total Generado KW]] -> 0.0013888889 | AC27: =+Tabla35[[#This Row],[MO Operación Máximo]]/Tabla35[[#This Row],[Total Generado KW]] -> 0.0013888889 | AD27: =+Tabla35[[#This Row],[MO Cierre Promedio]]/Tabla35[[#This Row],[Total Generado KW]] -> 0.00055555556 | AE27: =+Tabla35[[#This Row],[MO Cierre Máximo]]/Tabla35[[#This Row],[Total Generado KW]] -> 0.00055555556 | AF27: 300 | AG27: 300 | AH27: 25 | AI27: 25 | AJ27: 10 | AK27: 10 | AL27: -33.335041 | AM27: -70.707174
A28: PROYECTO ODATA DATACENTER | B28: Ver | C28: Metropolitana | D28: Lampa | E28: ODATA | F28: 271 | G28: Aprobado | H28: 186.00894 | I28: 44221.625 | J28: SGA Gestión Ambiental | K28: 10 | L28: 2000 | M28: =Tabla35[[#This Row],[P Generada (KW)]]*Tabla35[[#This Row],[GE Salas (Principal)]] -> 20000 | N28: 2 | O28: 2000 | P28: =Tabla35[[#This Row],[P Generada (KW)2]]*Tabla35[[#This Row],[GE Oficinas (Respaldo)]] -> 4000 | Q28: 840000 | R28: 701400 | S28: =+Tabla35[[#This Row],[Cantidad Diesel /kg]]/Tabla35[[#This Row],[Cantidad Diesel /L]] -> 0.835 | T28: 30 | U28: 7 | V28: 1250 | W28: =Tabla35[[#This Row],[Consumo (KW)3]]*Tabla35[[#This Row],[Cantidad Chillers]] -> 8750 | X28: =Tabla35[[#This Row],[Total Generado KW]]+Tabla35[[#This Row],[Total Generado KW2]] -> 24000 | Y28: =Tabla35[[#This Row],[Total Generado KW]]/1.5 -> 13333.333 | Z28: =+Tabla35[[#This Row],[MO Contrucción Promedio]]/Tabla35[[#This Row],[Total Generado KW]] -> 0.0095 | AA28: =+Tabla35[[#This Row],[MO Contrucción Máximo]]/Tabla35[[#This Row],[Total Generado KW]] -> 0.0185 | AB28: =+Tabla35[[#This Row],[MO Operación Promedio]]/Tabla35[[#This Row],[Total Generado KW]] -> 0.00325 | AC28: =+Tabla35[[#This Row],[MO Operación Máximo]]/Tabla35[[#This Row],[Total Generado KW]] -> 0.0062 | AD28: =+Tabla35[[#This Row],[MO Cierre Promedio]]/Tabla35[[#This Row],[Total Generado KW]] -> 0.00125 | AE28: =+Tabla35[[#This Row],[MO Cierre Máximo]]/Tabla35[[#This Row],[Total Generado KW]] -> 0.002 | AF28: 190 | AG28: 370 | AH28: 65 | AI28: 124 | AJ28: 25 | AK28: 40 | AL28: -33.26996 | AM28: -70.849966 | AP28: Regiones | AQ28: Proyectos
A29: DATACENTER SANTA TERESA | B29: Ver | C29: Metropolitana | D29: Lampa | E29: ODATA | F29: 217 | G29: Desistido | H29: 23.096157 | I29: 44120.625 | J29: SGA Gestión Ambiental | Z29: =+AVERAGE(Z12:Z28) -> 0.0047556636 | AA29: =+AVERAGE(AA12:AA28) -> 0.0074269329 | AB29: =+AVERAGE(AB12:AB28) -> 0.0010878289 | AC29: =+AVERAGE(AC12:AC28) -> 0.001803812 | AD29: =+AVERAGE(AD12:AD28) -> 0.00069646838 | AE29: =+AVERAGE(AE12:AE28) -> 0.0012067178 | AL29: -33.290326 | AM29: -70.743578 | AP29: Metropolitana | AQ29: 19
A30: Cerrillos Data Center | B30: Ver | C30: Metropolitana | D30: Cerrillos | E30: Dataluna | F30: 200 | G30: Renuncia RCA | H30: 212.96522 | I30: 43878.625 | J30: JACOBS Chile SA. / Inversiones y Servicios Dataluna Ltda. | AL30: -33.521596 | AM30: -70.722916 | AP30: Valparaíso | AQ30: 2
A31: Proyecto "Ampliación Edificio de Data Center y Oficinas SONDA, Parque Empresarial Aconcagua" | B31: Ver | C31: Metropolitana | D31: Quilicura | E31: Sonda S.A. | F31: 125 | G31: Aprobado | H31: 198.78296 | I31: 43384.625 | J31: TECCAP Ingeniería | Q31: 402100 | R31: 341785 | AL31: -33.26996 | AM31: -70.849966
A32: Ampliación Data Center PARAM | B32: Ver | C32: Metropolitana | D32: Quilicura | E32: Dataluna | F32: 140 | G32: Aprobado | H32: 152.77573 | I32: 43151.625 | J32: GrupoGestiona Consultores | AL32: -33.358428 | AM32: -70.692537 | AP32: Días de aprobación DIA | AQ32: Días
A33: Ampliación del Almacenamiento de Combustible Data Center Param | B33: Ver | C33: Metropolitana | D33: Quilicura | E33: Dataluna | F33: 5.2 | G33: Aprobado | H33: 401.13731 | I33: 42396.625 | J33: JACOBS Chile SA. / Inversiones y Servicios Dataluna Ltda. | AL33: -33.359343 | AM33: -70.698385 | AP33: Máximo | AQ33: =+MAX(H12:H18,H20:H24,H26:H28,H30:H35,H39) -> 527.10205
A34: Data Center III Entel -Pudahuel | B34: Ver | C34: Metropolitana | D34: Pudahuel | E34: Equinix | F34: 44 | G34: Aprobado | H34: 229.85103 | I34: 42114.625 | J34: Andalué Ambiental | AL34: -33.447638 | AM34: -70.851623 | AP34: Mínimo | AQ34: =+MIN(H12:H18,H20:H24,H26:H28,H30:H35,H39) -> 100.5
A35: Claro-Chile, Data Center Colina | B35: Ver | C35: Metropolitana | D35: Colina | E35: CLARO CHILE S.A. | F35: 85 | G35: Aprobado | H35: 320.5 | I35: 41157.625 | J35: MHO Consultores | K35: 16 | L35: 2200 | AL35: -33.241607 | AM35: -70.738958 | AP35: Mediana | AQ35: =+MEDIAN(H12:H18,H20:H24,H26:H28,H30:H35,H39) -> 212.96522
A36: DATA CENTER SONDA | B36: Ver | C36: Metropolitana | D36: Quilicura | E36: Sonda S.A. | F36: 20 | G36: Desistido | H36: 10.5 | I36: 40970.625 | AL36: -33.356623 | AM36: -70.698836 | AP36: Promedio | AQ36: =+AVERAGE(H12:H18,H20:H24,H26:H28,H30:H35,H39) -> 258.3693
A37: DATA CENTER SONDA | B37: Ver | C37: Metropolitana | D37: Quilicura | E37: Sonda S.A. | F37: 20 | G37: Desistido | H37: 12.5 | I37: 40959.625 | AL37: -33.356725 | AM37: -70.699371
A38: DATA CENTER SONDA | B38: Ver | C38: Metropolitana | D38: Quilicura | E38: Sonda S.A. | F38: 14.5 | G38: Desistido | H38: 47.5 | I38: 40911.625 | AL38: -33.355777 | AM38: -70.695382
A39: Regularización Data Center Hewlett Packard Chile Comercial Ltda. | B39: Ver | C39: Metropolitana | D39: Paine | E39: Digital holdings chile spa | F39: 31 | G39: Aprobado | H39: 100.5 | I39: 40877.625 | J39: MHO Consultores | AL39: -33.811285 | AM39: -70.748899
A40: Regularización Data Center Hewlett Packard Chile Ltda. | B40: Ver | C40: Metropolitana | D40: Paine | E40: Hewlett Packard Chile Comercial Ltda. | F40: 31 | G40: Desistido | H40: 13.5 | I40: 40765.667 | J40: MHO Consultores | AL40: -33.811282 | AM40: -70.749425
A41: Data center HP Chile | B41: Ver | C41: Metropolitana | D41: Paine | E41: Hewlett Packard Chile Comercial Ltda. | F41: 32 | G41: No Admitido a Tramitación | H41: 13.5 | I41: 40581.625 | J41: MHO Consultores | AL41: -33.812241 | AM41: -70.748834
Z42: mano d | AA42: Máximo P construcción | AB42: Promedio Operación | AC42: Máximo P Operación | AD42: Promedio Cierre | AE42: Máximo P Cierre
Y43: MMOO Promedio | Z43: =+Z29*120000 -> 570.67963 | AA43: =+AA29*120000 -> 891.23195 | AB43: =+AB29*120000 -> 130.53947 | AC43: =+AC29*120000 -> 216.45744 | AD43: =+AD29*120000 -> 83.576205 | AE43: =+AE29*120000 -> 144.80614
I44: GIZA | J44: 10
I45: ORBE | J45: 3
I46: MHO | J46: 5
I47: IT AMBIENTAL | J47: 2
I48: SGA GE AMBIENTAL | J48: 2 | Y48: pag 27 par3 | Z48: Fase | AA48: Mano de Obra Promedio | AB48: Mano de Obra Máxima
Z49: Construcción | AA49: =Z43 -> 570.67963 | AB49: =AA43 -> 891.23195
Z50: Operación | AA50: =AB43 -> 130.53947 | AB50: =AC43 -> 216.45744
Z51: Cierre o abandono | AA51: =AD43 -> 83.576205 | AB51: =AE43 -> 144.80614

Sheet DC Acceso abierto 2026
A1: Id | B1: Proyecto | C1: SI | D1: NUP | E1: Empresa Solicitante | F1: Tipo | G1: Estado Solicitud | H1: Fecha Recepción | I1: Capacidad [MW] | J1: Tipo Proyecto | K1: Fecha Estimada Conexión | L1: Punto de Conexión | M1: Nivel de tension | N1: Barra | O1: Paño | P1: Región | Q1: Comuna | R1: Segmento de Transmisión | S1: Fecha emisión informe definitivo | T1: Plazo obtención declaración en const | U1: Prórroga plazo obtención declaración en const.
A2: 2951 | B2: PE MAGUILLIN | E2: MAGUILLIN EOLICA SPA | F2: SUCTD | G2: Solicitud ingresada | I2: 70 | J2: Eólico | L2: línea 1x66kV Constitución - Planta Viñales | M2: 66 | N2: Derivación | O2: línea 1x66kV Constitución - Planta Viñales | P2: Maule | Q2: Constitución | R2: Dedicada
A3: 2950 | B3: SP LA ODISEA | E3: Icafal Lancuyen SpA | F3: SUCTD | G3: Solicitud ingresada | I3: 120 | J3: Híbrido | L3: LT CAMPO LINDO - SANTA CLARA 220 kV | M3: 220 | N3: Estructura N°4 | O3: Estructura N°4 | P3: Biobío | Q3: Los Ángeles | R3: Dedicada
A4: 2949 | B4: BESS Arwen | E4: Transmisión del Melado SpA | F4: SAC | G4: Solicitud Ingresada | I4: 350 | J4: Híbrido | L4: S/E Frontera 220kV | M4: 220 | N4: Interruptor y medio | O4: J9 | P4: Antofagasta | Q4: Maria Elena | R4: Nacional
A5: 2948 | B5: Tovaku Costa | E5: Sociedad Punta Del Cobre S.A. | F5: SUCTD | G5: Solicitud ingresada | I5: 12 | J5: Consumo | L5: S/E Central Tocopilla 110 kV | M5: 110 | N5: Barra Principal Sección 1 | O5: H2 | P5: Antofagasta | Q5: Tocopilla | R5: Dedicada
A6: 2947 | B6: Guanaco Solar | E6: Fotovoltaica Norte Grande 4 SpA | F6: SAC | G6: Solicitud Ingresada | I6: 76 | J6: Híbrido | L6: S/E Diego de Almagro | M6: 110 | N6: Barra principal 1 más transferencia | O6: H10 | P6: Atacama | Q6: Diego de Almagro | R6: Nacional
A7: 2946 | B7: SAE Volcán Guallatiri II | E7: PELICANO SpA | F7: SUCTD | G7: Solicitud ingresada | I7: 20 | J7: Híbrido | L7: S/E Elevadora SE Volcán Guallatiri | M7: 23 | N7: Barra 2 | O7: E4 | P7: Maule | Q7: Parral | R7: Dedicada
A8: 2945 | B8: Solar Millán Etapa II Almacenamiento | E8: BIWO Renovables S.A. | F8: FEHACIENTES | G8: Proyecto ingresado | I8: 95 | J8: Consumo | L8: S/E Solar Millán 23kV | M8: 23 | N8: Barra Principal 23kV | O8: B2 | P8: Metropolitana de Santiago | Q8: Lampa | R8: Dedicada
A9: 2944 | B9: Alimentador San Francisco | E9: CGE Transmisión S.A. | F9: SAC | G9: Solicitud Ingresada | I9: 5 | J9: Consumo | L9: S/E Cauquenes 66/13,2kV | M9: 13 | N9: Barra Principal asociada al transformador N°3 | O9: 52C1 | P9: Maule | Q9: Cauquenes | R9: Zonal
A10: 2943 | B10: SE Planta Cerrillos 110/23 kV 50 MVA | E10: Sociedad Contractual Minera Carola | F10: SUCTD | G10: Solicitud ingresada | I10: 50 | J10: Consumo | L10: Línea 110 kV Cardones - Refugio | M10: 110 | N10: Barra simple mas barra de transferencia | O10: H3 | P10: Atacama | Q10: Tierra Amarilla | R10: Dedicada
A11: 2942 | B11: BESS Arwen | D11: 7156 | E11: Transmisión del Melado SpA | F11: SAC | G11: Desistida | I11: 350 | J11: Híbrido | L11: S/E Frontera 220kV | M11: 220 | N11: Interruptor y medio | O11: J9 | P11: Antofagasta | Q11: Maria Elena | R11: Nacional
A12: 2941 | B12: Nuevo Alimentador Av Victoria | D12: 7154 | E12: CGE Transmisión S.A. | F12: SAC | G12: Evaluación Admisibilidad | I12: 9 | J12: Consumo | L12: SE Alameda 15kV | M12: 15 | N12: Barra N°3 | O12: C13 | P12: Libertador General Bernardo OHiggins | Q12: Rancagua | R12: Zonal
A13: 2940 | B13: Tovaku | D13: 7155 | E13: Sociedad Punta Del Cobre S.A. | F13: SAC | G13: Evaluación Admisibilidad | I13: 40 | J13: Consumo | L13: S/E Ana María 220 kV | M13: 220 | N13: Interruptor y Medio | O13: J11-J12, por definir según disponibilidad | P13: Antofagasta | Q13: Maria Elena | R13: Nacional
A14: 2939 | B14: Coihueco III | D14: 7151 | E14: 3 MW Desarrollo SpA | F14: SUCTD | G14: Evaluación Admisibilidad | I14: 170 | J14: Híbrido | L14: S/E San Fabián 220 kV | M14: 220 | N14: Barra Simple | O14: J4 | P14: Ñuble | Q14: Coihueco | R14: Dedicada
A15: 2938 | B15: Habilitación Retiros BESS Estepa | E15: Estepa Solar SpA | F15: FEHACIENTES | G15: Proyecto ingresado | I15: 230 | J15: Híbrido | L15: Subestación Estepa 220/33 kV | M15: 33 | N15: barra principal | O15: por definir | P15: Antofagasta | Q15: Maria Elena | R15: Dedicada
A16: 2937 | B16: PFV Semillero | D16: 7101 | E16: oEnergy Development SpA | F16: SUCTD | G16: Evaluación Admisibilidad | I16: 40 | J16: Híbrido | L16: Pozo Almonte - Cerro Colorado 110 kV | M16: 110 | N16: Conexión en Derivación | O16: Estructura sin numero | P16: Tarapacá | Q16: Pozo Almonte | R16: Dedicada
A17: 2936 | B17: BESS Halcón 2 | D17: 7100 | E17: oEnergy Development SpA | F17: SUCTD | G17: Evaluación Admisibilidad | I17: 57 | J17: Híbrido | L17: Pozo Almonte - Cerro Colorado 110 kV | M17: 110 | N17: Conexión en Derivación | O17: Estructura sin numero | P17: Tarapacá | Q17: Pozo Almonte | R17: Dedicada
A18: 2935 | B18: DDA BESS Expansión I | D18: 7152 | E18: Copiapó Solar S.A. | F18: FEHACIENTES | G18: Revisión de antecedentes | I18: 82.5 | J18: Solar | L18: S/E Desierto de Atacama 33 KV | M18: 33 | N18: Media Tensión | O18: Por definir | P18: Atacama | Q18: Tierra Amarilla | R18: Dedicada
A19: 2934 | B19: _x0003_Parque Eólico El Almendro | D19: 7099 | E19: Bioenergías Forestales SpA | F19: SAC | G19: Evaluación de antecedentes y/o requerimientos | I19: 144 | J19: Eólico | L19: SE Planta Rio Vergara 220kV | M19: 220 | N19: barra1 | O19: J5 | P19: La Araucanía | Q19: Renaico | R19: Nacional
A20: 2933 | B20: Puerto y Desaladora Minera Santo Domingo | D20: 7098 | E20: MInera Santo Domingo SCM | F20: SUCTD | G20: Audiencia y antecedentes adicionales | I20: 21.6 | J20: Consumo | L20: S/E Totoralillo 220kV | M20: 220 | N20: Barra simple | O20: J2 | P20: Atacama | Q20: Caldera | R20: Dedicada
A21: 2932 | B21: Sistema Almacenamiento Conejo BESS | D21: 7153 | E21: Conejo Solar SpA | F21: FEHACIENTES | G21: Revisión de antecedentes | I21: 104 | J21: Híbrido | L21: S/E Conejo 33 kV | M21: 33 | N21: Barra switchgear 33 kV | O21: CB1; CB2; CB3; CB4 | P21: Antofagasta | Q21: Taltal | R21: Dedicada
A22: 2931 | B22: BESS PFV Los Boldos Etapa 2 | E22: Longotoma Solar SpA. | F22: FEHACIENTES | G22: Proyecto ingresado | I22: 47 | J22: Híbrido | L22: Nueva S/E Elevadora PFV Los Boldos 220/33 kV | M22: 33 | N22: Switchgear en MT S/E Los Boldos 33 kV | O22: Por definir en ingenieria de detalles | P22: Valparaiso | Q22: La Ligua | R22: Dedicada
A23: 2930 | B23: Nuevo Alimentador El Rosario | E23: Litoral Transmisión S.A. | F23: SAC | G23: Solicitud Ingresada | I23: 10 | J23: Consumo | L23: Subestacion El Totoral 66/12 kV | M23: 12 | N23: Barra principal | O23: C1 | P23: Valparaiso | Q23: El Quisco | R23: Zonal
A24: 2929 | B24: Nuevo Alimentador El Rosario | D24: 7095 | E24: Litoral Transmisión S.A. | F24: SAC | G24: Clasificado como Obra Menor | I24: 10 | J24: Consumo | L24: Subestacion El Totoral 66/12 kV | M24: 12 | N24: Barra principal | O24: C1 | P24: Valparaiso | Q24: El Quisco | R24: Zonal | S24: 03/03/2026 00:00:00
A25: 2928 | B25: BESS Lo Pinto | D25: 7097 | E25: Campos del Canto SpA | F25: SAC | G25: Evaluación de antecedentes y/o requerimientos | I25: 50 | J25: Híbrido | P25: Metropolitana de Santiago | Q25: Colina | R25: Zonal
A26: 2927 | B26: Proyecto Ursa | E26: Sphera Development SpA | F26: SAC | G26: Solicitud Ingresada | I26: 90 | J26: Híbrido | L26: S/E Las Dichas 220 kV | M26: 220 | N26: Barra 2, diagonal 1 | O26: J3 | P26: Valparaiso | Q26: Casablanca | R26: Zonal
A27: 2926 | B27: Proyecto Ursa | D27: 7094 | E27: Sphera Development SpA | F27: SAC | G27: Rechazada | I27: 90 | J27: Híbrido | L27: S/E Las Dichas 220 kV | M27: 220 | N27: Barra 2, diagonal 1 | O27: J3 | P27: Valparaiso | Q27: Casablanca | R27: Zonal
A28: 2925 | B28: Nuevo Alimentador Encón | D28: 7093 | E28: Chilquinta Transmisión S.A. | F28: SAC | G28: Clasificado como Obra Menor | I28: 10 | J28: Consumo | L28: Subestacion San Felipe 12 kV | M28: 12 | N28: Barra 1 | O28: C9 | P28: Valparaiso | Q28: San Felipe | R28: Zonal
A29: 2924 | B29: BESS Los Castaños | D29: 7092 | E29: Enerblan SpA. | F29: FEHACIENTES | G29: Revisión de antecedentes | I29: 6.0 | J29: Solar | L29: S/E PV Los Castaños EXPV Duqueco | M29: 23 | N29: Tramo Línea S/E PV Los Castaños-PV Los Castaños | O29: Por definir | P29: Biobío | Q29: Los Ángeles | R29: Dedicada
A30: 2923 | B30: Nuevo Alimentador 12 kV Calbuco en S/E La Reina | D30: 7090 | E30: Enel Distribución Chile S.A. | F30: SAC | G30: Evaluación de antecedentes y/o requerimientos | I30: 8.3 | J30: Consumo | L30: S/E La Reina 12 kV | M30: 12 | N30: Barra 12 kV N°1 (celda) | O30: C5 | P30: Metropolitana de Santiago | Q30: Peñalolén | R30: Zonal
A31: 2922 | B31: Nuevo Alimentador 12 kV Choapa en S/E Panamericana | D31: 7091 | E31: Enel Distribución Chile S.A. | F31: SAC | G31: Evaluación de antecedentes y/o requerimientos | I31: 8.3 | J31: Consumo | L31: S/E Panamericana | M31: 12 | N31: Barra 12 kV N°3 (Patio) | O31: C19 | P31: Metropolitana de Santiago | Q31: San Bernardo | R31: Zonal
A32: 2921 | B32: BESS Lo Pinto | E32: Campos del Canto SpA | F32: SAC | G32: Desistida | I32: 50 | J32: Híbrido | P32: Metropolitana de Santiago | Q32: Colina | R32: Zonal
A33: 2920 | B33: Apolo | D33: 7089 | E33: Membrillo SpA | F33: SUCTD | G33: Evaluación Admisibilidad | I33: 80 | J33: Híbrido | L33: Linea Puente Negro - La Higuera 2x220kV | M33: 220 | N33: Barra principal | O33: por definir | P33: Libertador General Bernardo OHiggins | Q33: San Fernando | R33: Dedicada
A34: 2919 | B34: BESS Lo Pinto | E34: Campos del Canto SpA | F34: SAC | G34: Desistida | I34: 50 | J34: Híbrido | P34: Metropolitana de Santiago | Q34: Colina | R34: Zonal
A35: 2918 | B35: BESS Lo Pinto | E35: Campos del Canto SpA | F35: SAC | G35: Desistida | I35: 50 | J35: Híbrido | P35: Metropolitana de Santiago | Q35: Colina | R35: Zonal
A36: 2917 | B36: BESS Lo Pinto | E36: Campos del Canto SpA | F36: SAC | G36: Desistida | I36: 50 | J36: Híbrido | P36: Metropolitana de Santiago | Q36: Colina | R36: Zonal
A37: 2916 | B37: BESS Lo Pinto | E37: Campos del Canto SpA | F37: SAC | G37: Desistida | I37: 50 | J37: Híbrido | P37: Metropolitana de Santiago | Q37: Colina | R37: Zonal
A38: 2915 | B38: BESS Lo Pinto | E38: Campos del Canto SpA | F38: SAC | G38: Desistida | I38: 50 | J38: Híbrido | P38: Metropolitana de Santiago | Q38: Colina | R38: Zonal
A39: 2914 | B39: BESS Lo Pinto | E39: Campos del Canto SpA | F39: SAC | G39: Desistida | I39: 50 | J39: Híbrido | P39: Metropolitana de Santiago | Q39: Colina | R39: Zonal
A40: 2913 | B40: BESS Lo Pinto | E40: Campos del Canto SpA | F40: SAC | G40: Desistida | I40: 50 | J40: Híbrido | P40: Metropolitana de Santiago | Q40: Colina | R40: Zonal
A41: 2912 | B41: BESS ANGOL | D41: 7082 | E41: Espinos S.A. | F41: SUCTD | G41: Evaluación Admisibilidad | I41: 4.5 | J41: Híbrido | L41: S/E Angol | M41: 23 | N41: Línea 1x23 [kV] Angol-Tap Off Renaico (cerca de estructura 418) | O41: E2 | P41: La Araucanía | Q41: Angol | R41: Dedicada
A42: 2911 | B42: PFV+BESS Kleos | D42: 7081 | E42: Mytilineos BESS Chile SpA. | F42: SUCTD | G42: Evaluación Admisibilidad | I42: 100 | J42: Híbrido | L42: L1 2x220 Guacolda-Maitencillo | M42: 220 | N42: Seccionamiento de línea | O42: C2, entre estructuras 80 y 81 | P42: Atacama | Q42: Freirina | R42: Dedicada
A43: 2910 | B43: Explotación de Sulfuros Radomiro Tomic Fase II | D43: 7080 | E43: Codelco (Corporación Nacional del Cobre) | F43: SAC | G43: Evaluación de antecedentes y/o requerimientos | I43: 150 | J43: Consumo | L43: S/E CRUCERO | M43: 220 | N43: Barra 2 | O43: J18 | P43: Antofagasta | Q43: Calama | R43: Nacional
A44: 2909 | B44: BESS Espiga De Oro | D44: 7088 | E44: Enerblan SpA. | F44: FEHACIENTES | G44: Revisión de antecedentes | I44: 2.5 | J44: Solar | L44: S/E PFV Espiga De Oro | M44: 23 | N44: Tramo Línea | O44: 52E1 | P44: Biobío | Q44: Negrete | R44: Dedicada
A45: 2908 | B45: BESS Kleos | E45: Mytilineos BESS Chile SpA. | F45: SUCTD | G45: Desistida | I45: 100 | J45: Híbrido | L45: LAT L1 2x220 kV Guacolda-Maitencillo | M45: 220 | N45: Seccionamiento de línea | O45: C2,entre estructura 80 y 81 | P45: Atacama | Q45: Freirina | R45: Dedicada
A46: 2907 | B46: Actualización de Subestaciones Las Luces y Planta Óxido - Suministro Agua, Taltal, Región de Antofagasta | D46: 7087 | E46: Minera Las Cenizas S.A. | F46: FEHACIENTES | G46: Revisión de antecedentes | I46: 18 | J46: Consumo | L46: s/e Las Luces y s/e Planta Óxido | M46: 110 | N46: barra simple | O46: existente | P46: Antofagasta | Q46: Taltal | R46: Dedicada
A47: 2906 | B47: Los Mesías Solar | D47: 7078 | E47: Inversiones y Desarrollos Energéticos Free Power SpA. | F47: SAC | G47: Desarrollo de estudios y/o antecedentes | I47: 89 | J47: Solar | L47: Quinquimo | M47: 110 | N47: BP | O47: H4 | P47: Valparaiso | Q47: Papudo | R47: Zonal
A48: 2905 | B48: Minera Comahue | D48: 7076 | E48: Next Minerals S.A. | F48: SUCTD | G48: Evaluación Admisibilidad | I48: 3 | J48: Consumo | L48: Linea 13,8kV Zaturno Capricornio | M48: 13 | N48: derivación | O48: C1 | P48: Antofagasta | Q48: Antofagasta | R48: Dedicada
A49: 2904 | B49: Minera Comahue | E49: Next Minerals S.A. | F49: SUCTD | G49: Solicitud ingresada | I49: 3 | J49: Consumo | L49: Linea 13,8kV Zaturno Capricornio | M49: 13 | N49: derivación | O49: C1 | P49: Antofagasta | Q49: Antofagasta | R49: Dedicada
A50: 2903 | B50: Proyecto Ursa | D50: 7077 | E50: Sphera Development SpA | F50: SAC | G50: Rechazada | I50: 90 | J50: Híbrido | L50: S/E Las Dichas 220 kV | M50: 220 | N50: Diagonal 1 | O50: J3 | P50: Valparaiso | Q50: Casablanca | R50: Zonal
A51: 2902 | B51: Parque Eólico El Almendro | D51: 7079 | E51: Bioenergías Forestales SpA | F51: SAC | G51: Rechazada | I51: 144 | J51: Eólico | L51: S/E PLANTA RIO VERGARA 220 KV | M51: 220 | N51: Barra 1 | O51: JL5 | P51: La Araucanía | Q51: Renaico | R51: Nacional
A52: 2901 | B52: Sol de Linares | D52: 7075 | E52: Sphera Development SpA | F52: SAC | G52: Rechazada | I52: 20 | J52: Híbrido | L52: S/E Valentín Letelier | M52: 66 | N52: Barra Principal | O52: B4 | P52: Maule | Q52: Linares | R52: Zonal
A53: 2900 | B53: Don Ambrosio Solar | D53: 7059 | E53: Inversiones y Desarrollos Energéticos Free Power SpA. | F53: SAC | G53: Rechazada | I53: 50 | J53: Solar | L53: Lo Aguirre | M53: 23 | N53: BP + T | O53: E26 y E27 | P53: Metropolitana de Santiago | Q53: Curacaví | R53: Zonal
A54: 2899 | B54: Parque Fotovoltaico Estrella Fugaz | D54: 7057 | E54: Comercial Técnica Limitada | F54: SAC | G54: Rechazada | I54: 90 | J54: Solar | L54: Subestación Loica 220 kV | M54: 220 | N54: Barra principal | O54: H1 | P54: Libertador General Bernardo OHiggins | Q54: Litueche | R54: Zonal
A55: 2898 | B55: BESS Don Lucas | D55: 7058 | E55: Los Maitenes Solar SpA | F55: SAC | G55: Detenida a la espera de información técnica del propietario de la instalación | I55: 89 | J55: Híbrido | L55: Nueva S/E Don Melchor | M55: 110 | N55: BPS2 + T | O55: H6 | P55: Metropolitana de Santiago | Q55: Pirque | R55: Zonal
A56: 2896 | B56: Meseta de los Andes BESS | D56: 7056 | E56: Tercera Region Solar SpA | F56: FEHACIENTES | G56: Proyecto autorizado para declararse en construcción | I56: 160 | J56: Híbrido | L56: Meseta de Los Andes 220/33kV | M56: 33 | N56: Barra principal | O56: nivel E | P56: Valparaiso | Q56: Calle Larga | R56: Dedicada | T56: 02/2028
A57: 2895 | B57: BESS PE Atacama | D57: 7048 | E57: Parque Eólico Atacama SpA | F57: FEHACIENTES | G57: Proyecto Fehaciente debe presentar SUCTD | I57: 165.3 | J57: Híbrido | L57: S/E IberAtacama 33 kV | M57: 33 | N57: Barras de Instalaciones de Generación en 33 kV | O57: PA S/E IberAtacama 33 kV | P57: Atacama | Q57: Freirina | R57: Dedicada
A58: 2894 | B58: BESS PE Atacama | D58: 7047 | E58: Parque Eólico Atacama SpA | F58: SUCTD | G58: Audiencia y antecedentes adicionales | I58: 165.3 | J58: Híbrido | L58: S/E IberAtacama | M58: 33 | N58: Barras de Instalaciones de Generación en 33 kV | O58: PA S/E IberAtacama 33 kV | P58: Atacama | Q58: Freirina | R58: Dedicada
A59: 2893 | B59: BESS Parque Fotovoltaico Pedro de Valdivia Etapa 2 | D59: 7046 | E59: Solar PDV SpA | F59: FEHACIENTES | G59: Revisión de antecedentes | I59: 72 | J59: Híbrido | L59: Nueva S/E Elevadora Pedro de Valdivia 33 kV | M59: 33 | N59: barra simple | O59: E10, E11, E12 | P59: Antofagasta | Q59: Maria Elena | R59: Dedicada
A60: 2892 | B60: Central Sol del Loa II | E60: GM Renewables Holdings SpA | F60: SAC | G60: Desistida | I60: 500 | J60: Híbrido | L60: S/E Frontera 220kV | M60: 220 | N60: Barra Principal N°2 | O60: J18/J17 | P60: Antofagasta | Q60: Maria Elena | R60: Nacional
A61: 2891 | B61: Central Sol del Loa II | D61: 7045 | E61: GM Renewables Holdings SpA | F61: SAC | G61: Desarrollo de estudios y/o antecedentes | I61: 500 | J61: Híbrido | L61: S/E Frontera 220kV | M61: 220 | N61: Barra Principal N°2 | O61: J18/J17 | P61: Antofagasta | Q61: Maria Elena | R61: Nacional
A62: 2890 | B62: CONEXIÓN INSTALACIONES DE FAENAS (II.FF.) CENTRAL DE BOMBEO | D62: 7044 | E62: Colbún S.A. | F62: SAC | G62: Rechazada | I62: 10 | J62: Consumo | L62: S/E Paranal 66 kV | M62: 66 | N62: Barra Principal | O62: E1 | P62: Antofagasta | Q62: Taltal | R62: Nacional
A63: 2889 | B63: AR CHANGOS SOLAR II | D63: 7042 | E63: AR ENERGIA CHILE SPA | F63: FEHACIENTES | G63: Proyecto calificado como fehaciente | I63: 20 | J63: Híbrido | L63: S/E AR CHANGOS SOLAR 33/220 | M63: 33 | N63: switchgear 33kV | O63: Celdas de MT por definir | P63: Antofagasta | Q63: Mejillones | R63: Dedicada
A64: 2888 | B64: Parque Eólico Calbuco | D64: 7041 | E64: Energy Intersol Calbuco | F64: SAC | G64: Detenida a la espera de definición de ingeniería de la obra | I64: 49.6 | J64: Eólico | L64: SE Ilque | M64: 110 | N64: barra principal y transferencia | O64: H1 | P64: Los Lagos | Q64: Calbuco | R64: Zonal
A65: 2887 | B65: SISTEMA DE ALMACENAMIENTO DE ENERGÍA STANDALONE EN BATERÍAS EN LA PLANTA DE ÁCIDO SULFÚRICO MEJILLONES 10 MW | D65: 7040 | E65: Noracid S.A. | F65: SUCTD | G65: Audiencia y antecedentes adicionales | I65: 10 | J65: Híbrido | L65: S/E Mejillones 13,8 kV | M65: 13 | N65: Barra de 13,8 kV de la Subestación Mejillones | O65: CB4 | P65: Antofagasta | Q65: Mejillones | R65: Dedicada
A66: 2886 | B66: PV Las Baronesas | D66: 7036 | E66: Sungrow Power Chile SpA | F66: SAC | G66: Desarrollo de estudios y/o antecedentes | I66: 90 | J66: Solar | L66: Los Varones | M66: 220 | N66: Diagonal J4-J5 | O66: J4-J5 | P66: Biobío | Q66: Los Ángeles | R66: Nacional
A67: 2885 | B67: BESS Don Lucas | D67: 7037 | E67: Los Maitenes Solar SpA | F67: SAC | G67: Rechazada | I67: 89 | J67: Híbrido | L67: Nueva S/E Don Melchor | M67: 110 | N67: BPS1 | O67: H6 | P67: Metropolitana de Santiago | Q67: Pirque | R67: Zonal
A68: 2884 | B68: NUEVO PAÑO DE ALIMENTADOR "MIRAFLORES" | E68: Chilquinta Transmisión S.A. | F68: SAC | G68: Solicitud Ingresada | I68: 10 | J68: Consumo | L68: Linares Norte 13,2 kV | M68: 13 | N68: Barra principal, sección 2 | O68: C4 | P68: Maule | Q68: Linares | R68: Zonal
A69: 2883 | B69: NUEVO PAÑO DE ALIMENTADOR "MIRAFLORES" | D69: 7035 | E69: Chilquinta Transmisión S.A. | F69: SAC | G69: Clasificado como Obra Menor | I69: 10 | J69: Consumo | L69: Linares Norte 13,2 kV | M69: 13 | N69: Barra principal, sección 2 | O69: C4 | P69: Maule | Q69: Linares | R69: Zonal
A70: 2882 | B70: REPOTENCIAMIENTO ELECTRICO SAR (SANTA FILOMENA) | D70: 7043 | E70: Anglo American Sur S.A. | F70: SUCTD | G70: Audiencia y antecedentes adicionales | I70: 23.7 | J70: Consumo | L70: S/E SANTA FILOMENA | M70: 220 | N70: Barra Principal | O70: JT2 | P70: Metropolitana de Santiago | Q70: Colina | R70: Dedicada
A71: 2881 | B71: Reconversión CTM2 | D71: 7021 | E71: Engie Energía Chile S.A. | F71: FEHACIENTES | G71: Proyecto autorizado para declararse en construcción | I71: 156.6 | J71: Híbrido | L71: S/E Chacaya 220 kV | M71: 220 | N71: Barra Principal | O71: JG2 | P71: Antofagasta | Q71: Mejillones | R71: Dedicada | T71: 03/2028
A72: 2880 | B72: Reconversión CTM1 | D72: 7020 | E72: Engie Energía Chile S.A. | F72: FEHACIENTES | G72: Proyecto autorizado para declararse en construcción | I72: 146.5 | J72: Híbrido | L72: S/E Chacaya 220 kV | M72: 220 | N72: Barra Principal | O72: JG1 | P72: Antofagasta | Q72: Mejillones | R72: Dedicada | T72: 03/2028
A73: 2879 | B73: AMPLIACION MEGA DATA CENTER LAMPA ETAPA 2 | C73: 1 | D73: 7034 | E73: Electrica Santa Teresa SpA | F73: FEHACIENTES | G73: Proyecto autorizado para declararse en construcción | H73: 46021 | I73: 300 | J73: Consumo | K73: 48502 | L73: Santa Teresa | M73: 220 | N73: Barra 220 kV | O73: JT1 | P73: Metropolitana de Santiago | Q73: Lampa | R73: Dedicada | T73: 02/2028
A74: 2878 | B74: Conexión Alimentador Ruta 5 Lado Sur a Paño E4 - SE Reloncaví | D74: 7019 | E74: Sociedad Austral de Transmisión Troncal | F74: SAC | G74: Detenida a la espera de definición de ingeniería de la obra | I74: 9.9 | J74: Consumo | L74: SE Reloncaví 23 kV | M74: 23 | N74: Barra Principal, Sección 1 | O74: E4 | P74: Los Lagos | Q74: Puerto Montt | R74: Zonal
A75: 2877 | B75: Conexión Alimentador Ruta 5 Lado Norte a Paño E3 - SE Reloncaví | D75: 7018 | E75: Sociedad Austral de Transmisión Troncal | F75: SAC | G75: Detenida a la espera de definición de ingeniería de la obra | I75: 3.8 | J75: Consumo | L75: SE Reloncaví 23 kV | M75: 23 | N75: Barra Principal, Sección 1 | O75: E3 | P75: Los Lagos | Q75: Puerto Montt | R75: Zonal
A76: 2876 | B76: Conexión Alimentador Altos de Tepual a Paño E2 - SE Reloncaví | D76: 7017 | E76: Sociedad Austral de Transmisión Troncal | F76: SAC | G76: Detenida a la espera de definición de ingeniería de la obra | I76: 5.8 | J76: Consumo | L76: SE Reloncaví 23 kV | M76: 23 | N76: Barra Principal, Sección 1 | O76: E2 | P76: Los Lagos | Q76: Puerto Montt | R76: Zonal
A77: 2875 | B77: Conexión Alimentador Los Notros a Paño E1 - SE Reloncaví | D77: 7016 | E77: Sociedad Austral de Transmisión Troncal | F77: SAC | G77: Detenida a la espera de definición de ingeniería de la obra | I77: 6.8 | J77: Consumo | L77: SE Reloncaví 23 kV | M77: 23 | N77: Barra Principal, Sección 1 | O77: E1 | P77: Los Lagos | Q77: Puerto Montt | R77: Zonal
A78: 2874 | B78: Conexión Alimentador Bunster a Paño C3 - SE Deuco | D78: 7015 | E78: Sistema de Transmisión del Sur S.A. | F78: SAC | G78: Clasificado como Obra Menor | I78: 3.2 | J78: Consumo | L78: SE Deuco 13,2 kV | M78: 13 | N78: Barra Principal, Sección 1 | O78: C3 | P78: La Araucanía | Q78: Angol | R78: Zonal
A79: 2873 | B79: Traslado Alimentador 12 kV Fruna en S/E Bicentenario | D79: 7014 | E79: Enel Distribución Chile S.A. | F79: SAC | G79: Desarrollo de estudios y/o antecedentes | I79: 8.3 | J79: Consumo | L79: S/E Bicentenario 12 kV | M79: 12 | N79: Barra 12 kV N°3 (celda) | O79: C19 | P79: Metropolitana de Santiago | Q79: Maipú | R79: Zonal
A80: 2872 | B80: Nuevo Alimentador 23 kV Velardi en S/E Lampa | D80: 7013 | E80: Enel Distribución Chile S.A. | F80: SAC | G80: Desarrollo de estudios y/o antecedentes | I80: 12 | J80: Consumo | L80: S/E Lampa 23 kV | M80: 23 | N80: Barra 23 kV N°4 (celda) | O80: E28 | P80: Metropolitana de Santiago | Q80: Lampa | R80: Zonal
A81: 2871 | B81: Nuevo Alimentador 12 kV Perdices en S/E Macul | D81: 7012 | E81: Enel Distribución Chile S.A. | F81: SAC | G81: Desarrollo de estudios y/o antecedentes | I81: 8.3 | J81: Consumo | L81: S/E Macul 12 kV | M81: 12 | N81: Barra 12 kV N°1 (celda) | O81: C7 | P81: Metropolitana de Santiago | Q81: Peñalolén | R81: Zonal
A82: 2870 | B82: Nuevo Alimentador 12 kV Villagra en S/E La Reina | D82: 7011 | E82: Enel Distribución Chile S.A. | F82: SAC | G82: Desarrollo de estudios y/o antecedentes | I82: 8.3 | J82: Consumo | L82: S/E La Reina 12 kV | M82: 12 | N82: Barra 12 kV N°1 (Celda) | O82: C4 | P82: Metropolitana de Santiago | Q82: Peñalolén | R82: Zonal
A83: 2869 | B83: Nuevo Alimentador 23 kV Merino en S/E Lo Boza | D83: 7010 | E83: Enel Distribución Chile S.A. | F83: SAC | G83: Evaluación de antecedentes y/o requerimientos | I83: 12 | J83: Consumo | L83: S/E Lo Boza 23 kV | M83: 23 | N83: Barra 23 kV N°6 (Celda) | O83: E46 | P83: Metropolitana de Santiago | Q83: Renca | R83: Zonal
A84: 2868 | B84: BESS Rocío | D84: 7009 | E84: Trinergy SpA | F84: SAC | G84: Desarrollo de estudios y/o antecedentes | I84: 20 | J84: Híbrido | L84: Nueva Panquehue | M84: 12 | N84: Barra BP1 | O84: Paño C4 Por Definir | P84: Valparaiso | Q84: Panquehue | R84: Zonal
A85: 2867 | B85: BESS Vicuña | D85: 7033 | E85: Sunergy Chile SpA | F85: SUCTD | G85: Detenida a la espera de información técnica del propietario de la instalación | I85: 60 | J85: Híbrido | L85: LTx Damascal - Minera Arqueros | M85: 110 | N85: Tapoff E1 | O85: H3 Damascal | P85: Coquimbo | Q85: Vicuña | R85: Dedicada
A86: 2866 | B86: PE PEWMA | D86: 7008 | E86: Akuo Energy Chile SpA | F86: SUCTD | G86: Rechazada | I86: 120 | J86: Eólico | L86: S/E Colaco | M86: 110 | N86: Barra Principal | O86: HL2 | P86: Los Lagos | Q86: Calbuco | R86: Dedicada
A87: 2865 | B87: Finis Terrae II | D87: 7007 | E87: Enel Green Power del Sur | F87: FEHACIENTES | G87: Proyecto autorizado para declararse en construcción | I87: 100 | J87: Híbrido | L87: Rande 33 kV | M87: 33 | N87: Switchgear | O87: Por definir | P87: Antofagasta | Q87: Maria Elena | R87: Dedicada | T87: 09/2027
A88: 2864 | B88: BESS San Esteban | D88: 6274 | E88: Mako Inversiones SpA. | F88: SAC | G88: Desarrollo de estudios y/o antecedentes | I88: 350 | J88: Híbrido | L88: SE Los Maquis 220kV | M88: 220 | N88: Barra Principal 1 y 2 | O88: J11 y J12 | P88: Valparaiso | Q88: Los Andes | R88: Nacional
A89: 2863 | B89: BESS Chinchilla | D89: 6273 | E89: Chinchilla SPA | F89: SUCTD | G89: Desistida | I89: 100 | J89: Híbrido | L89: Derivación Pajonales - Don Hector | M89: 220 | N89: Paño E11 | O89: Paño E11 | P89: Atacama | Q89: Vallenar | R89: Dedicada
A90: 2862 | B90: BESS Chinchilla | D90: 6273 | E90: Chinchilla SPA | F90: SUCTD | G90: Observaciones al informe CTD preliminar | I90: 100 | J90: Híbrido | L90: Derivación Pajonales - Don Hector | M90: 220 | N90: Paño E11 | O90: Paño E11 | P90: Atacama | Q90: Vallenar | R90: Dedicada
A91: 2861 | B91: PV+SAE Zafiro | D91: 6272 | E91: INVERSIONES MSF 24 SPA | F91: SAC | G91: Desarrollo de estudios y/o antecedentes | I91: 210 | J91: Híbrido | L91: S/E Frontera 220 kV | M91: 220 | N91: Barra principal | O91: J24 | P91: Antofagasta | Q91: Maria Elena | R91: Nacional
A92: 2860 | B92: BESS PE Cabo Leones III | D92: 6276 | E92: IBEREÓLICA CABO LEONES III SpA | F92: SUCTD | G92: Elaboración Informe CTD preliminar | I92: 190.2 | J92: Híbrido | L92: S/E Central Parque Eólico Cabo Leones I en 33 kV | M92: 33 | N92: Barra 33 kV del Paño propiedad de Parque Eólico Cabo Leones III en S/E Central Parque Eólico Cabo Leones I | O92: Paño JT2 propiedad de Parque Eólico Cabo Leones III | P92: Atacama | Q92: Freirina | R92: Dedicada
A93: 2859 | B93: BESS PE CABO LEONES III | D93: 6275 | E93: IBEREÓLICA CABO LEONES III SpA | F93: FEHACIENTES | G93: Proyecto Fehaciente debe presentar SUCTD | I93: 190.2 | J93: Híbrido | L93: S/E Central Parque Eólico Cabo Leones I en 33 kV | M93: 33 | N93: Barra 33 kV del Paño propiedad de Parque Eólico Cabo Leones III en S/E Central Parque Eólico Cabo Leones I | O93: Paño JT2 propiedad de Parque Eólico Cabo Leones III | P93: Atacama | Q93: Freirina
A94: 2857 | B94: Ampliación BESS Coya | D94: 6263 | E94: Engie Energía Chile S.A. | F94: FEHACIENTES | G94: Revisión de antecedentes | I94: 60 | J94: Híbrido | L94: S/E Palpana 33 kV | M94: 33 | N94: barra 33 kV | O94: 33 kV | P94: Antofagasta | Q94: Maria Elena | R94: Dedicada
A95: 2856 | B95: ACS DC SANTIAGO I | C95: 1 | D95: 6264 | E95: ACS Data Center | F95: SAC | G95: Detenida a la espera de definición de ingeniería de la obra | H95: 46003 | I95: 14 | J95: Consumo | K95: 46965 | L95: S/E Chacabuco | M95: 23 | N95: Barra Principal 23 kV TR N°9 | O95: E66 | P95: Metropolitana de Santiago | Q95: Quilicura | R95: Zonal
A96: 2855 | B96: ACS DC SANTIAGO II | C96: 1 | D96: 6265 | E96: ACS Data Center | F96: SAC | G96: Detenida a la espera de definición de ingeniería de la obra | H96: 46003 | I96: 40 | J96: Consumo | K96: 47330 | L96: S/E Punta Verde | M96: 110 | N96: Barra Principal | O96: H21 y H24 | P96: Metropolitana de Santiago | Q96: Quilicura | R96: Zonal
A97: 2854 | B97: ACS DC SANTIAGO I | C97: 1 | E97: ACS Data Center | F97: SAC | G97: Desistida | I97: 14 | J97: Consumo | L97: S/E Chacabuco | M97: 23 | N97: Barra Principal 23 kV TR N°9 | O97: H67 | P97: Metropolitana de Santiago | Q97: Quilicura | R97: Zonal
A98: 2853 | B98: ACS DC SANTIAGO I | C98: 1 | D98: 6266 | E98: ACS Data Center | F98: SAC | G98: Detenida a la espera de definición de ingeniería de la obra | H98: 46003 | I98: 14 | J98: Consumo | K98: 46965 | L98: S/E Chacabuco | M98: 23 | N98: Barra Principal 23 kV TR N°9 | O98: H67 | P98: Metropolitana de Santiago | Q98: Quilicura | R98: Zonal
A99: 2852 | B99: ACS DC SANTIAGO I | C99: 1 | E99: ACS Data Center | F99: SAC | G99: Desistida | I99: 14 | J99: Consumo | P99: Metropolitana de Santiago | Q99: Quilicura | R99: Zonal
A100: 2851 | B100: Parque Fotovoltaico + BESS Posada | D100: 6262 | E100: Engie Energía Chile S.A. | F100: SAC | G100: Elaboración Informe de Autorización de Conexión Preliminar | I100: 100 | J100: Híbrido | L100: S/E Crucero | M100: 220 | N100: Barra Principal | O100: J18 | P100: Antofagasta | Q100: Maria Elena | R100: Nacional
...
